Workbook
Name COSTES_ELEGIBLES_MAS_IVA_NO_DEDUCIBLE_ELEGIBLE: Resumen!#REF!,Resumen!#REF!,Resumen!#REF!
Name COSTES_ELEGIBLES_MAS_IVA_NO_DEDUCIBLE_ELEGIBLE: #REF!,#REF!,#REF!
Name COSTES_NO_ELEGIBLES_MAS_IVA_NO_DEDUCIBLE_NO_ELEGIBLE: Resumen!$E$21:$E$24,Resumen!$E$25:$E$25
Name COSTES_NO_ELEGIBLES_MAS_IVA_NO_DEDUCIBLE_NO_ELEGIBLE: #REF!,#REF!
Name IVA: Referencias!$B$26
Name IVA_NO_DEDUCIBLE: Referencias!$B$27
Name PORCENTAJE_MARGINAL: Referencias!$B$28

Sheet Datos generales
A2: DATOS GENERALES PRESTACIÓN DE VARIANTE SERVICIO CIENTÍFICO-TÉCNICO
B4: DATOS GENERALES
A5: Instituto/Centro/Unidad | B5: (Campo desplegable)
A6: Servicio
A7: Cod. Servicio
A8: Prestación
A9: Nombre variante
A11: Unidad de Medida de Coste -UMC- (€/unidad)* | B11: (Campo desplegable) | C11: <--- Especificar Unidad de Medida de Coste del desplegable
A12: Número de unidades incluidas en la variante | B12: (Campo desplegable)
A13: Breve descripción de la Unidad de Medida de Coste
A14: *Las UMC predeterminadas en el desplegable deberían cubrir el 100% de las necesidades existentes, y se han reducido para simplificar la hoja de cálculo. En casos excepcionales se podrá solicitar la creación de nuevas unidades de medida de coste, que deberán ser aprobadas antes de su uso a través de ayuda.servicios@csic.es
B15: DATOS DE LA VARIANTE A INCLUIR
B16: LA VARIANTE INCLUYE | C16: HOJAS A RELLENAR
A17: Personal | B17: (Campo desplegable) | C17: =IF(B17="(Campo desplegable)","",IF(B17="SÍ","RELLENAR LA HOJA 'PERSONAL' DE ESTE FORMULARIO","NO DEBE COMPLETAR LA HOJA 'PERSONAL' DE ESTE FORMULARIO"))
A18: Equipamiento | B18: (Campo desplegable) | C18: =IF(B18="(Campo desplegable)","",IF(B18="SÍ","RELLENAR LA HOJA 'EQUIPAMIENTO' DE ESTE FORMULARIO","NO DEBE COMPLETAR LA HOJA 'EQUIPAMIENTO' DE ESTE FORMULARIO"))
A19: Instalación/Infraestructura | B19: (Campo desplegable) | C19: =IF(B19="(Campo desplegable)","",IF(B19="SÍ","RELLENAR LA HOJA 'INSTALACIÓN-INFRAESTRUCTURA' DE ESTE FORMULARIO","NO DEBE COMPLETAR LA HOJA 'INSTALACIÓN-INFRAESTRUCTURA' DE ESTE FORMULARIO"))
A20: Otros | B20: (Campo desplegable) | C20: =IF(B20="(Campo desplegable)","",IF(B20="SÍ","RELLENAR LA HOJA 'OTROS' DE ESTE FORMULARIO","NO DEBE COMPLETAR LA HOJA 'OTROS' DE ESTE FORMULARIO"))

Sheet Resumen
A2: RESUMEN COSTES UNITARIOS SERVICIOS CIENTÍFICO-TÉCNICOS
A4: UMC (€) | C4: =IF('Datos generales'!B11="(Campo desplegable)","Indicar en la hoja de 'Datos generales'",'Datos generales'!B11) -> Indicar en la hoja de 'Datos generales'
A6: Incremento para AGE/OPIs/Universidades (%) | C6: 5
A7: Incremento para otros usuarios (%) | C7: 15
A9: COSTE TOTAL (€) | D9: =B27+E27 -> 0
A10: TARIFAS INTERNAS
A11: Para solicitudes del propio centro (€) | D11: =C27*(1+IVA*IVA_NO_DEDUCIBLE) -> 0
A12: Para solicitudes del resto de centros del CSIC (€) | D12: =D11+(D11*PORCENTAJE_MARGINAL) -> 0
A13: FACTURAS
A14: ="Para solicitudes AGE/OPIs/Universidades " & $C$6 &"% (€)" -> Para solicitudes AGE/OPIs/Universidades 5% (€) | D14: =IF(D17<0.3,D9*(1+C6/100),D9) -> 0
A15: ="Para otros usuarios "&$C$7 &"% (€)" -> Para otros usuarios 15% (€) | D15: =IF(D17<0.3,D9*(1+C7/100),D9) -> 0
A17: Porcentaje del coste de amortizaciones sobre el coste total | D17: =IF(D27=0,0,D27/D9) -> 0
A19: DESGLOSE DE COSTES DE LA VARIANTE
A20: CONCEPTOS | B20: COSTES ELEGIBLES PROYECTOS PROGRAMA MARCO (€) | C20: COSTES MARGINALES (€) | D20: COSTES AMORTIZACIÓN (€) | E20: Coste NO elegible (€)
A21: PERSONAL | B21: =Personal!$I$30 -> 0 | C21: NO APLICA | D21: NO APLICA | E21: =Personal!$J$30 -> 0
A22: EQUIPAMIENTO | B22: =Equipamiento!F21 -> 0 | C22: =Equipamiento!H21 -> 0 | D22: =Equipamiento!I21 -> 0 | E22: =Equipamiento!$G$21 -> 0
A23: INSTALACIONES/INFRAESTRUCTURAS | B23: ='Instalación-Infraestructura'!$I$79 -> 0 | C23: ='Instalación-Infraestructura'!$K$79 -> 0 | D23: NO APLICA | E23: ='Instalación-Infraestructura'!$J$79 -> 0
A24: OTROS | B24: =Otros!$G$72 -> 0 | C24: =Otros!$I$72 -> 0 | D24: NO APLICA | E24: =Otros!$H$72 -> 0
A25: IVA NO DEDUCIBLE | B25: =SUM(B22:B24)*IVA*IVA_NO_DEDUCIBLE -> 0 | C25: NO APLICA | D25: NO APLICA | E25: =SUM(E22:E24)*IVA*IVA_NO_DEDUCIBLE -> 0
A26: COSTES INDIRECTOS (23,5% de la suma de costes elegibles y no elegibles) | B26: NO APLICA | C26: NO APLICA | D26: NO APLICA | E26: =(B21+B22+B23+B24+B25+E21+E22+E23+E24+E25)*23.5/100 -> 0
A27: COSTE TOTAL (€) | B27: =SUM(B21:B25) -> 0 | C27: =SUM(C22:C24) -> 0 | D27: =D22 -> 0 | E27: =SUM(E21:E26) -> 0

Sheet Personal
A2: PERSONAL (por UMC)
A4: UMC (€) | B4: =IF('Datos generales'!B11:C11="(Campo desplegable)","Indicar en la hoja de 'Datos generales'",'Datos generales'!B11:C11) -> Indicar en la hoja de 'Datos generales'
B7: Lista desplegable tipo personal (véase "Tabla costes personal" en "Referencias") | C7: Coste/hora según tipo personal (€) | D7: Nº horas y fracción/UMC | E7: Importe (€)
A8: 1. PERSONAL CSIC DE PLANTILLA (funcionarios y laborales fijos) | I8: ELEGIBLE EUROPEOS | J8: NO ELEGIBLE EUROPEOS | K8: MARGINAL | L8: AMORTIZACIÓN
A9: Coste/hora x tiempo | B9: (Campo desplegable) | C9: =IF(B9="(Campo desplegable)",0,VLOOKUP(B9,Referencias!$A$3:$B$17,2,FALSE)) -> 0 | D9: 0 | E9: =(C9*D9) -> 0 | G9: COSTE TOTAL (UMC) PERSONAL DE PLANTILLA (€) | I9: X
A10: Coste/hora x tiempo | B10: (Campo desplegable) | C10: =IF(B10="(Campo desplegable)",0,VLOOKUP(B10,Referencias!$A$3:$B$17,2,FALSE)) -> 0 | D10: 0 | E10: =(C10*D10) -> 0 | I10: X
A11: Coste/hora x tiempo | B11: (Campo desplegable) | C11: =IF(B11="(Campo desplegable)",0,VLOOKUP(B11,Referencias!$A$3:$B$17,2,FALSE)) -> 0 | D11: 0 | E11: =(C11*D11) -> 0 | I11: X
A12: Coste/hora x tiempo | B12: (Campo desplegable) | C12: =IF(B12="(Campo desplegable)",0,VLOOKUP(B12,Referencias!$A$3:$B$17,2,FALSE)) -> 0 | D12: 0 | E12: =(C12*D12) -> 0 | G12: =SUMIF($E$9:$E$13,">0",$E$9:$E$13) -> 0 | I12: X
A13: Coste/hora x tiempo | B13: (Campo desplegable) | C13: =IF(B13="(Campo desplegable)",0,VLOOKUP(B13,Referencias!$A$3:$B$17,2,FALSE)) -> 0 | D13: 0 | E13: =(C13*D13) -> 0 | I13: X
A14: 2. PERSONAL CSIC CONTRATADO
A15: Coste/hora x tiempo | B15: (Campo desplegable) | C15: =IF(B15="(Campo desplegable)",0,VLOOKUP(B15,Referencias!$C$3:$D$15,2,FALSE)) -> 0 | D15: 0 | E15: =(C15*D15) -> 0 | G15: COSTE TOTAL (UMC) PERSONAL CONTRATADO (€) | I15: X
A16: Coste/hora x tiempo | B16: (Campo desplegable) | C16: =IF(B16="(Campo desplegable)",0,VLOOKUP(B16,Referencias!$C$3:$D$15,2,FALSE)) -> 0 | D16: 0 | E16: =(C16*D16) -> 0 | I16: X
A17: Coste/hora x tiempo | B17: (Campo desplegable) | C17: =IF(B17="(Campo desplegable)",0,VLOOKUP(B17,Referencias!$C$3:$D$15,2,FALSE)) -> 0 | D17: 0 | E17: =(C17*D17) -> 0 | I17: X
A18: Coste/hora x tiempo | B18: (Campo desplegable) | C18: =IF(B18="(Campo desplegable)",0,VLOOKUP(B18,Referencias!$C$3:$D$15,2,FALSE)) -> 0 | D18: 0 | E18: =(C18*D18) -> 0 | G18: =SUMIF($E$15:$E$19,">0",$E$15:$E$19) -> 0 | I18: X
A19: Coste/hora x tiempo | B19: (Campo desplegable) | C19: =IF(B19="(Campo desplegable)",0,VLOOKUP(B19,Referencias!$C$3:$D$15,2,FALSE)) -> 0 | D19: 0 | E19: =(C19*D19) -> 0 | I19: X
A20: 3. PERSONAL CSIC ASOCIADO A CONCEPTOS NO ELEGIBLES
A21: Coste/hora x tiempo | B21: (Campo desplegable) | C21: =IF(B21="(Campo desplegable)",0,VLOOKUP(B21,Referencias!$E$3:$F$21,2,FALSE)) -> 0 | D21: 0 | E21: =(C21*D21) -> 0 | G21: COSTE TOTAL (UMC) PERSONAL CSIC ASOCIADO A CONCEPTOS NO ELEGIBLES (€) | J21: X
A22: Coste/hora x tiempo | B22: (Campo desplegable) | C22: =IF(B22="(Campo desplegable)",0,VLOOKUP(B22,Referencias!$E$3:$F$21,2,FALSE)) -> 0 | D22: 0 | E22: =(C22*D22) -> 0 | J22: X
A23: Coste/hora x tiempo | B23: (Campo desplegable) | C23: =IF(B23="(Campo desplegable)",0,VLOOKUP(B23,Referencias!$E$3:$F$21,2,FALSE)) -> 0 | D23: 0 | E23: =(C23*D23) -> 0 | J23: X
A24: Coste/hora x tiempo | B24: (Campo desplegable) | C24: =IF(B24="(Campo desplegable)",0,VLOOKUP(B24,Referencias!$E$3:$F$21,2,FALSE)) -> 0 | D24: 0 | E24: =(C24*D24) -> 0 | G24: =SUMIF($E$21:$E$25,">0",$E$21:$E$25) -> 0 | J24: X
A25: Coste/hora x tiempo | B25: (Campo desplegable) | C25: =IF(B25="(Campo desplegable)",0,VLOOKUP(B25,Referencias!$E$3:$F$21,2,FALSE)) -> 0 | D25: 0 | E25: =(C25*D25) -> 0 | J25: X
A27: 4. PERSONAL NO CSIC (FUNCIONARIO/LABORAL) Cumplimentar únicamente en caso de CENTROS MIXTOS | B27: En caso de centros mixtos, estimación del coste TOTAL del personal NO CSIC interviniente por UMC según datos que aporten las entidades integradas en el centro | E27: 0 | J27: X
B29: COSTE TOTAL (UMC) PERSONAL | E29: TOTAL IMPORTE(€) | I29: TOTAL ELEGIBLE EUROPEOS (€) | J29: TOTAL NO ELEGIBLE EUROPEOS (€) | K29: TOTAL MARGINAL (€) | L29: TOTAL AMORTIZACIÓN (€)
B30: Según tabla aprobada de costes unitarios (en casos no tabulados según coste-empresa salarial real) aplicada al tiempo de intervención de cada persona interviniente en el desarrollo de la variante | E30: =SUM(E9:E13,E15:E19,E21:E25,E27) -> 0 | I30: =SUMIF(I9:I27,"X",$E$9:$E$27) -> 0 | J30: =SUMIF(J9:J27,"X",$E$9:$E$27) -> 0 | K30: =SUMIF(K9:K27,"X",$E$9:$E$27) -> 0 | L30: =SUMIF(L9:L27,"X",$E$9:$E$27) -> 0

Sheet Instalación-Infraestructura
A2: INFRAESTRUCTURAS (por UMC)
A4: UMC (€) | B4: =IF('Datos generales'!B11:C11="(Campo desplegable)","Indicar en la hoja de 'Datos generales'",'Datos generales'!B11:C11) -> Indicar en la hoja de 'Datos generales'
B6: INSTALACIÓN/INFRAESTRUCTURA UTILIZADO (específica que actúe de modo indivisible en la prestación) | F6: IR AL APARTADO DE INSTALACIÓN/INFRAESTRUCTURA
A7: INSTALACIÓN/INFRAESTRUCTURA 1 | B7: Campo rellenable de descripción de la instalación/infraestructura | E7: → | F7: IR A INSTALACIÓN/INFRAESTRUCTURA 1
A8: INSTALACIÓN/INFRAESTRUCTURA 2 | B8: Campo rellenable de descripción de la instalación/infraestructura | E8: → | F8: IR A INSTALACIÓN/INFRAESTRUCTURA 2
A9: INSTALACIÓN/INFRAESTRUCTURA 3 | B9: Campo rellenable de descripción de la instalación/infraestructura | E9: → | F9: IR A INSTALACIÓN/INFRAESTRUCTURA 3
A10: INSTALACIÓN/INFRAESTRUCTURA 4 | B10: Campo rellenable de descripción de la instalación/infraestructura | E10: → | F10: IR A INSTALACIÓN/INFRAESTRUCTURA 4
A12: =IF(B7="Campo rellenable de descripción de la instalación/infraestructura","Campo automático",A7&": "&B7) -> Campo automático | B12: DESCRIPCIÓN DE LA UTILIZACIÓN
A13: Uso de la instalación/infraestructura 1 (específica que actúe de modo indivisible en la prestación) | B13: Información para el cálculo del coste
A14: Energía | B14: Indique si la energía es: -Medida con un contador y valorada con las tarifas del contrato de suministro vigente -Estimada mediante facturas | D14: (Campo desplegable) | I14: ELEGIBLE EUROPEOS | J14: NO ELEGIBLE EUROPEOS | K14: MARGINAL | L14: AMORTIZACIÓN
B15: Coste de energía por UMC - IMPORTE SIN IVA (€) | D15: 0 | I15: =IF(D14="Medida con un contador","X","") | J15: =IF(D14="Estimada mediante facturas","X","") | K15: X
A16: Fungibles/Fluidos (para cada tipo o grupo de fungibles/fluidos consumidos con el uso de la instalación/infraestructura) | B16: Incluir los costes - IMPORTE SIN IVA (€): Contables, número de fungibles o grupos de fungibles por coste unidad/grupo (según facturas/mercado) | D16: 0 | I16: X | K16: X
B17: Breve descripción de fungibles/fluidos utilizados ->
B18: Incluir los costes - IMPORTE SIN IVA (€): No contables (continuos), medida de consumo (directa o indirecta/calculada) por coste UMC | D18: 0 | I18: X | K18: X
B19: Breve descripción de fungibles/fluidos utilizados ->
B20: Incluir los costes - IMPORTE SIN IVA (€): No contables (continuos), estimación de consumo sin medidas reales por coste UMC según factura o precio de mercado | D20: 0 | J20: X | K20: X
B21: Breve descripción de fungibles/fluidos utilizados ->
A22: Participación de la infraestructura en convocatorias "Integrating and opening research infrastructures of European interest" | B22: ¿La infraestructura participa en convocatorias "Integrating and opening research infrastructures of European interest"? | D22: (Campo desplegable)
A23: Costes de gestión | B23: Costes del proveedor y contratos de gestión (seguridad, seguros, control de calidad y certificación...) - IMPORTE SIN IVA (€) | D23: 0 | I23: =IF($D$22="SI","X","") | J23: =IF($D$22="NO","X","")
B24: Inversión de capital (costes de alquiler, amortización de edificios o de instrumentación…) - IMPORTE SIN IVA (€) | D24: 0 | J24: =IF(OR(D22="(Campo desplegable)",D22="SI"),"","X")
A25: Servicios generales y científicos | B25: Los que estén específicamente incluidos en el acceso (gastos de envío, licencias de software...) - IMPORTE SIN IVA (€) | D25: 0 | I25: =IF($D$22="SI","X","") | J25: =IF($D$22="NO","X","") | K25: X
A26: Mantenimiento y reparación | B26: Incluye la limpieza específica, calibraciones y pruebas - IMPORTE SIN IVA (€) | D26: 0 | I26: =IF($D$22="SI","X","") | J26: =IF($D$22="NO","X","")
A27: COSTE TOTAL UTILIZACIÓN DE LA INSTALACIÓN/INFRAESTRUCTURA 1 POR UMC | B27: → | D27: =IF(D22="SI",SUM(D15,D16,D18,D20,D23,D25,D26),SUM(D15,D16,D18,D20,D23:D26)) -> 0
A28: =IF(B8="Campo rellenable de descripción de la instalación/infraestructura","Campo automático",A8&": "&B8) -> Campo automático | F28: VOLVER ARRIBA
A29: Uso de la instalación/infraestructura 2 (específica que actúe de modo indivisible en la prestación) | B29: Información para el cálculo del coste
A30: Energía | B30: Indique si la energía es: -Medida con un contador y valorada con las tarifas del contrato de suministro vigente -Estimada mediante facturas | D30: (Campo desplegable)
B31: Coste de energía por UMC - IMPORTE SIN IVA (€) | D31: 0 | I31: =IF($D30="Medida con un contador","X","") | J31: =IF($D30="Estimada mediante facturas","X","") | K31: X
A32: Fungibles/Fluidos (para cada tipo o grupo de fungibles/fluidos consumidos con el uso de la instalación/infraestructura) | B32: Incluir los costes - IMPORTE SIN IVA (€): Contables, número de fungibles o grupos de fungibles por coste unidad/grupo (según facturas/mercado) | D32: 0 | I32: X | K32: X
B33: Breve descripción de fungibles/fluidos utilizados ->
B34: Incluir los costes - IMPORTE SIN IVA (€): No contables (continuos), medida de consumo (directa o indirecta/calculada) por coste UMC | D34: 0 | I34: X | K34: X
B35: Breve descripción de fungibles/fluidos utilizados ->
B36: Incluir los costes - IMPORTE SIN IVA (€): No contables (continuos), estimación de consumo sin medidas reales por coste UMC según factura o precio de mercado | D36: 0 | J36: X | K36: X
B37: Breve descripción de fungibles/fluidos utilizados ->
A38: Participación de la infraestructura en convocatorias "Integrating and opening research infrastructures of European interest" | B38: ¿La infraestructura participa en convocatorias "Integrating and opening research infrastructures of European interest"? | D38: (Campo desplegable)
A39: Costes de gestión | B39: Costes del proveedor y contratos de gestión (seguridad, seguros, control de calidad y certificación...) - IMPORTE SIN IVA (€) | D39: 0 | I39: =IF($D38="SI","X","") | J39: =IF($D38="NO","X","")
B40: Inversión de capital (costes de alquiler, amortización de edificios o de instrumentación…) - IMPORTE SIN IVA (€) | D40: 0 | J40: =IF(OR(D38="(Campo desplegable)",D38="SI"),"","X")
A41: Servicios generales y científicos | B41: Los que estén específicamente incluidos en el acceso (gastos de envío, licencias de software...) - IMPORTE SIN IVA (€) | D41: 0 | I41: =IF($D38="SI","X","") | J41: =IF($D38="NO","X","") | K41: X
A42: Mantenimiento y reparación | B42: Incluye la limpieza específica, calibraciones y pruebas - IMPORTE SIN IVA (€) | D42: 0 | I42: =IF($D38="SI","X","") | J42: =IF($D38="NO","X","")
A43: COSTE TOTAL UTILIZACIÓN DE LA INSTALACIÓN/INFRAESTRUCTURA 2 POR UMC | B43: → | D43: =IF(D38="SI",SUM(D31,D32,D34,D36,D39,D41,D42),SUM(D31,D32,D34,D36,D39:D42)) -> 0
A44: =IF(B9="Campo rellenable de descripción de la instalación/infraestructura","Campo automático",A9&": "&B9) -> Campo automático | F44: VOLVER ARRIBA
A45: Uso de la instalación/infraestructura 3 (específica que actúe de modo indivisible en la prestación) | B45: Información para el cálculo del coste
A46: Energía | B46: Indique si la energía es: -Medida con un contador y valorada con las tarifas del contrato de suministro vigente -Estimada mediante facturas | D46: (Campo desplegable)
B47: Coste de energía por UMC - IMPORTE SIN IVA (€) | D47: 0 | I47: =IF($D46="Medida con un contador","X","") | J47: =IF($D46="Estimada mediante facturas","X","") | K47: X
A48: Fungibles/Fluidos (para cada tipo o grupo de fungibles/fluidos consumidos con el uso de la instalación/infraestructura) | B48: Incluir los costes - IMPORTE SIN IVA (€): Contables, número de fungibles o grupos de fungibles por coste unidad/grupo (según facturas/mercado) | D48: 0 | I48: X | K48: X
B49: Breve descripción de fungibles/fluidos utilizados ->
B50: Incluir los costes - IMPORTE SIN IVA (€): No contables (continuos), medida de consumo (directa o indirecta/calculada) por coste UMC | D50: 0 | I50: X | K50: X
B51: Breve descripción de fungibles/fluidos utilizados ->
B52: Incluir los costes - IMPORTE SIN IVA (€): No contables (continuos), estimación de consumo sin medidas reales por coste UMC según factura o precio de mercado | D52: 0 | J52: X | K52: X
B53: Breve descripción de fungibles/fluidos utilizados ->
A54: Participación de la infraestructura en convocatorias "Integrating and opening research infrastructures of European interest" | B54: ¿La infraestructura participa en convocatorias "Integrating and opening research infrastructures of European interest"? | D54: (Campo desplegable)
A55: Costes de gestión | B55: Costes del proveedor y contratos de gestión (seguridad, seguros, control de calidad y certificación...) - IMPORTE SIN IVA (€) | D55: 0 | I55: =IF($D54="SI","X","") | J55: =IF($D54="NO","X","")
B56: Inversión de capital (costes de alquiler, amortización de edificios o de instrumentación…) - IMPORTE SIN IVA (€) | D56: 0 | J56: =IF(OR(D54="(Campo desplegable)",D54="SI"),"","X")
A57: Servicios generales y científicos | B57: Los que estén específicamente incluidos en el acceso (gastos de envío, licencias de software...) - IMPORTE SIN IVA (€) | D57: 0 | I57: =IF($D54="SI","X","") | J57: =IF($D54="NO","X","") | K57: X
A58: Mantenimiento y reparación | B58: Incluye la limpieza específica, calibraciones y pruebas - IMPORTE SIN IVA (€) | D58: 0 | I58: =IF($D54="SI","X","") | J58: =IF($D54="NO","X","")
A59: COSTE TOTAL UTILIZACIÓN DE LA INSTALACIÓN/INFRAESTRUCTURA 3 POR UMC | B59: → | D59: =IF(D54="SI",SUM(D47,D48,D50,D52,D55,D57,D58),SUM(D47,D48,D50,D52,D55:D58)) -> 0
A60: =IF(B10="Campo rellenable de descripción de la instalación/infraestructura","Campo automático",A10&": "&B10) -> Campo automático | F60: VOLVER ARRIBA
A61: Uso de la instalación/infraestructura 4 (específica que actúe de modo indivisible en la prestación) | B61: Información para el cálculo del coste
A62: Energía | B62: Indique si la energía es: -Medida con un contador y valorada con las tarifas del contrato de suministro vigente -Estimada mediante facturas | D62: (Campo desplegable)
B63: Coste de energía por UMC - IMPORTE SIN IVA (€) | D63: 0 | I63: =IF($D62="Medida con un contador","X","") | J63: =IF($D62="Estimada mediante facturas","X","") | K63: X
A64: Fungibles/Fluidos (para cada tipo o grupo de fungibles/fluidos consumidos con el uso de la instalación/infraestructura) | B64: Incluir los costes - IMPORTE SIN IVA (€): Contables, número de fungibles o grupos de fungibles por coste unidad/grupo (según facturas/mercado) | D64: 0 | I64: X | K64: X
B65: Breve descripción de fungibles/fluidos utilizados ->
B66: Incluir los costes - IMPORTE SIN IVA (€): No contables (continuos), medida de consumo (directa o indirecta/calculada) por coste UMC | D66: 0 | I66: X | K66: X
B67: Breve descripción de fungibles/fluidos utilizados ->
B68: Incluir los costes - IMPORTE SIN IVA (€): No contables (continuos), estimación de consumo sin medidas reales por coste UMC según factura o precio de mercado | D68: 0 | J68: X | K68: X
B69: Breve descripción de fungibles/fluidos utilizados ->
A70: Participación de la infraestructura en convocatorias "Integrating and opening research infrastructures of European interest" | B70: ¿La infraestructura participa en convocatorias "Integrating and opening research infrastructures of European interest"? | D70: (Campo desplegable)
A71: Costes de gestión | B71: Costes del proveedor y contratos de gestión (seguridad, seguros, control de calidad y certificación...) - IMPORTE SIN IVA (€) | D71: 0 | I71: =IF($D70="SI","X","") | J71: =IF($D70="NO","X","")
B72: Inversión de capital (costes de alquiler, amortización de edificios o de instrumentación…) - IMPORTE SIN IVA (€) | D72: 0 | J72: =IF(OR(D70="(Campo desplegable)",D70="SI"),"","X")
A73: Servicios generales y científicos | B73: Los que estén específicamente incluidos en el acceso (gastos de envío, licencias de software...) - IMPORTE SIN IVA (€) | D73: 0 | I73: =IF($D70="SI","X","") | J73: =IF($D70="NO","X","") | K73: X
A74: Mantenimiento y reparación | B74: Incluye la limpieza específica, calibraciones y pruebas - IMPORTE SIN IVA (€) | D74: 0 | I74: =IF($D70="SI","X","") | J74: =IF($D70="NO","X","")
A75: COSTE TOTAL UTILIZACIÓN DE LA INSTALACIÓN/INFRAESTRUCTURA 4 POR UMC | B75: → | D75: =IF(D70="SI",SUM(D63,D64,D66,D68,D71,D73,D74),SUM(D63,D64,D66,D68,D71:D74)) -> 0
B78: COSTE TOTAL (UMC) INSTALACIONES/INFRAESTRUCTURAS | D78: TOTAL IMPORTE SIN IVA (€) | F78: VOLVER ARRIBA | I78: TOTAL ELEGIBLE EUROPEOS (€) | J78: TOTAL NO ELEGIBLE EUROPEOS (€) | K78: TOTAL MARGINAL (€) | L78: TOTAL AMORTIZACIÓN (€)
B79: Suma del coste total de instalaciones/infraestructuras implicado en el desarrollo por UMC | D79: =SUM(D27,D43,D59,D75) -> 0 | I79: =SUMIF(I15:I74,"X",$D$15:$D$74) -> 0 | J79: =SUMIF(J15:J74,"X",$D$15:$D$74) -> 0 | K79: =SUMIF(K15:K74,"X",$D$15:$D$74) -> 0 | L79: =SUMIF(L15:L74,"X",$D$15:$D$74) -> 0

Sheet Equipamiento
A2: EQUIPAMIENTO (por UMC)
A4: UMC (€) | B4: =IF('Datos generales'!B11:C11="(Campo desplegable)","Indicar en la hoja de 'Datos generales'",'Datos generales'!B11:C11) -> Indicar en la hoja de 'Datos generales'
B6: INDIQUE EL Nº DE EQUIPOS A USAR
B7: (Campo desplegable)
F8: TOTAL COSTES EQUIPAMIENTO
A9: EQUIPOS | B9: EQUIPO UTILIZADO | C9: IR A LA HOJA DEL EQUIPO | D9: TOTAL IMPORTE SIN IVA (€) | F9: TOTAL ELEGIBLE EUROPEOS (€) | G9: TOTAL NO ELEGIBLE EUROPEOS (€) | H9: TOTAL MARGINAL (€) | I9: TOTAL AMORTIZACIÓN (€)
A10: Nº 1 | B10: Campo rellenable de descripción del equipo | C10: IR A EQUIPO 1 | D10: ='Equipo 1'!$D$56 -> 0 | F10: ='Equipo 1'!$F$56 -> 0 | G10: ='Equipo 1'!$G$56 -> 0 | H10: ='Equipo 1'!$H$56 -> 0 | I10: ='Equipo 1'!$I$56 -> 0
A11: Nº 2 | B11: Campo rellenable de descripción del equipo | C11: IR A EQUIPO 2 | D11: ='Equipo 2'!D56 -> 0 | F11: ='Equipo 2'!$F$56 -> 0 | G11: ='Equipo 2'!$G$56 -> 0 | H11: ='Equipo 2'!$H$56 -> 0 | I11: ='Equipo 2'!$I$56 -> 0
A12: Nº 3 | B12: Campo rellenable de descripción del equipo | C12: IR A EQUIPO 3 | D12: ='Equipo 3'!D56 -> 0 | F12: ='Equipo 3'!$F$56 -> 0 | G12: ='Equipo 3'!$G$56 -> 0 | H12: ='Equipo 3'!$H$56 -> 0 | I12: ='Equipo 3'!$I$56 -> 0
A13: Nº 4 | B13: Campo rellenable de descripción del equipo | C13: IR A EQUIPO 4 | D13: ='Equipo 4'!D56 -> 0 | F13: ='Equipo 4'!$F$56 -> 0 | G13: ='Equipo 4'!$G$56 -> 0 | H13: ='Equipo 4'!$H$56 -> 0 | I13: ='Equipo 4'!$I$56 -> 0
A14: Nº 5 | B14: Campo rellenable de descripción del equipo | C14: IR A EQUIPO 5 | D14: ='Equipo 5'!D56 -> 0 | F14: ='Equipo 5'!$F$56 -> 0 | G14: ='Equipo 5'!$G$56 -> 0 | H14: ='Equipo 5'!$H$56 -> 0 | I14: ='Equipo 5'!$I$56 -> 0
A15: Nº 6 | B15: Campo rellenable de descripción del equipo | C15: IR A EQUIPO 6 | D15: ='Equipo 6'!D56 -> 0 | F15: ='Equipo 6'!$F$56 -> 0 | G15: ='Equipo 6'!$G$56 -> 0 | H15: ='Equipo 6'!$H$56 -> 0 | I15: ='Equipo 6'!$I$56 -> 0
A16: Nº 7 | B16: Campo rellenable de descripción del equipo | C16: IR A EQUIPO 7 | D16: ='Equipo 7'!D56 -> 0 | F16: ='Equipo 7'!$F$56 -> 0 | G16: ='Equipo 7'!$G$56 -> 0 | H16: ='Equipo 7'!$H$56 -> 0 | I16: ='Equipo 7'!$I$56 -> 0
A17: Nº 8 | B17: Campo rellenable de descripción del equipo | C17: IR A EQUIPO 8 | D17: ='Equipo 8'!D56 -> 0 | F17: ='Equipo 8'!$F$56 -> 0 | G17: ='Equipo 8'!$G$56 -> 0 | H17: ='Equipo 8'!$H$56 -> 0 | I17: ='Equipo 8'!$I$56 -> 0
A18: Nº 9 | B18: Campo rellenable de descripción del equipo | C18: IR A EQUIPO 9 | D18: ='Equipo 9'!D56 -> 0 | F18: ='Equipo 9'!$F$56 -> 0 | G18: ='Equipo 9'!$G$56 -> 0 | H18: ='Equipo 9'!$H$56 -> 0 | I18: ='Equipo 9'!$I$56 -> 0
A19: Nº 10 | B19: Campo rellenable de descripción del equipo | C19: IR A EQUIPO 10 | D19: ='Equipo 10'!D56 -> 0 | F19: ='Equipo 10'!$F$56 -> 0 | G19: ='Equipo 10'!$G$56 -> 0 | H19: ='Equipo 10'!$H$56 -> 0 | I19: ='Equipo 10'!$I$56 -> 0
C21: COSTE TOTAL (UMC) EQUIPAMIENTO | D21: =IF(B7=1,$D$10,IF(B7=2,SUMIF($D$10:$D$11,">0",$D$10:$D$11),IF(B7=3,SUMIF($D$10:$D$12,">0",$D$10:$D$12),IF(B7=4,SUMIF($D$10:$D$13,">0",$D$10:$D$13),IF(B7=5,SUMIF($D$10:$D$14,">0",$D$10:$D$14),IF(B7=6,SUMIF($D$10:$D$15,">0",$D$10:$D$15),IF(B7=7,SUMIF($D$10:$D$16,">0",$D$10:$D$16),IF(B7=8,SUMIF($D$10:$D$17,">0",$D$10:$D$17),IF(B7=9,SUMIF($D$10:$D$18,">0",$D$10:$D$18),SUMIF($D$10:$D$19,">0",$D$10:$D$19)))))))))) -> 0 | F21: =IF(B7=1,$F$10,IF(B7=2,SUMIF($F$10:$F$11,">0",$F$10:$F$11),IF(B7=3,SUMIF($F$10:$F$12,">0",$F$10:$F$12),IF(B7=4,SUMIF($F$10:$F$13,">0",$F$10:$F$13),IF(B7=5,SUMIF($F$10:$F$14,">0",$F$10:$F$14),IF(B7=6,SUMIF($F$10:$F$15,">0",$F$10:$F$15),IF(B7=7,SUMIF($F$10:$F$16,">0",$F$10:$F$16),IF(B7=8,SUMIF($F$10:$F$17,">0",$F$10:$F$17),IF(B7=9,SUMIF($F$10:$F$18,">0",$F$10:$F$18),SUMIF($F$10:$F$19,">0",$F$10:$F$19)))))))))) -> 0 | G21: =IF(B7=1,$G$10,IF(B7=2,SUMIF($G$10:$G$11,">0",$G$10:$G$11),IF(B7=3,SUMIF($G$10:$G$12,">0",$G$10:$G$12),IF(B7=4,SUMIF($G$10:$G$13,">0",$G$10:$G$13),IF(B7=5,SUMIF($G$10:$G$14,">0",$G$10:$G$14),IF(B7=6,SUMIF($G$10:$G$15,">0",$G$10:$G$15),IF(B7=7,SUMIF($G$10:$G$16,">0",$G$10:$G$16),IF(B7=8,SUMIF($G$10:$G$17,">0",$G$10:$G$17),IF(B7=9,SUMIF($G$10:$G$18,">0",$G$10:$G$18),SUMIF($G$10:$G$19,">0",$G$10:$G$19)))))))))) -> 0 | H21: =IF(B7=1,$H$10,IF(B7=2,SUMIF($H$10:$H$11,">0",$H$10:$H$11),IF(B7=3,SUMIF($H$10:$H$12,">0",$H$10:$H$12),IF(B7=4,SUMIF($H$10:$H$13,">0",$H$10:$H$13),IF(B7=5,SUMIF($H$10:$H$14,">0",$H$10:$H$14),IF(B7=6,SUMIF($H$10:$H$15,">0",$H$10:$H$15),IF(B7=7,SUMIF($H$10:$H$16,">0",$H$10:$H$16),IF(B7=8,SUMIF($H$10:$H$17,">0",$H$10:$H$17),IF(B7=9,SUMIF($H$10:$H$18,">0",$H$10:$H$18),SUMIF($H$10:$H$19,">0",$H$10:$H$19)))))))))) -> 0 | I21: =IF(B7=1,$I$10,IF(B7=2,SUMIF($I$10:$I$11,">0",$I$10:$I$11),IF(B7=3,SUMIF($I$10:$I$12,">0",$I$10:$I$12),IF(B7=4,SUMIF($I$10:$I$13,">0",$I$10:$I$13),IF(B7=5,SUMIF($I$10:$I$14,">0",$I$10:$I$14),IF(B7=6,SUMIF($I$10:$I$15,">0",$I$10:$I$15),IF(B7=7,SUMIF($I$10:$I$16,">0",$I$10:$I$16),IF(B7=8,SUMIF($I$10:$I$17,">0",$I$10:$I$17),IF(B7=9,SUMIF($I$10:$I$18,">0",$I$10:$I$18),SUMIF($I$10:$I$19,">0",$I$10:$I$19)))))))))) -> 0
F25: UTILIZACIÓN
F26: TOTAL ELEGIBLE EUROPEOS (€) | G26: TOTAL NO ELEGIBLE EUROPEOS (€) | H26: TOTAL MARGINAL (€) | I26: TOTAL AMORTIZACIÓN (€)
F27: ='Equipo 1'!F27 -> 0 | G27: ='Equipo 1'!G27 -> 0 | H27: ='Equipo 1'!H27 -> 0 | I27: ='Equipo 1'!I27 -> 0 | J27: EQUIPO 1
F28: ='Equipo 2'!F27 -> 0 | G28: ='Equipo 2'!G27 -> 0 | H28: ='Equipo 2'!H27 -> 0 | I28: ='Equipo 2'!I27 -> 0 | J28: EQUIPO 2
F29: ='Equipo 3'!F27 -> 0 | G29: ='Equipo 3'!G27 -> 0 | H29: ='Equipo 3'!H27 -> 0 | I29: ='Equipo 3'!I27 -> 0 | J29: EQUIPO 3
F30: ='Equipo 4'!F27 -> 0 | G30: ='Equipo 4'!G27 -> 0 | H30: ='Equipo 4'!H27 -> 0 | I30: ='Equipo 4'!I27 -> 0 | J30: EQUIPO 4
F31: ='Equipo 5'!F27 -> 0 | G31: ='Equipo 5'!G27 -> 0 | H31: ='Equipo 5'!H27 -> 0 | I31: ='Equipo 5'!I27 -> 0 | J31: EQUIPO 5
F32: ='Equipo 6'!F27 -> 0 | G32: ='Equipo 6'!G27 -> 0 | H32: ='Equipo 6'!H27 -> 0 | I32: ='Equipo 6'!I27 -> 0 | J32: EQUIPO 6
F33: ='Equipo 7'!F27 -> 0 | G33: ='Equipo 7'!G27 -> 0 | H33: ='Equipo 7'!H27 -> 0 | I33: ='Equipo 7'!I27 -> 0 | J33: EQUIPO 7
F34: ='Equipo 8'!F27 -> 0 | G34: ='Equipo 8'!G27 -> 0 | H34: ='Equipo 8'!H27 -> 0 | I34: ='Equipo 8'!I27 -> 0 | J34: EQUIPO 8
F35: ='Equipo 9'!F27 -> 0 | G35: ='Equipo 9'!G27 -> 0 | H35: ='Equipo 9'!H27 -> 0 | I35: ='Equipo 9'!I27 -> 0 | J35: EQUIPO 9
F36: ='Equipo 10'!F27 -> 0 | G36: ='Equipo 10'!G27 -> 0 | H36: ='Equipo 10'!H27 -> 0 | I36: ='Equipo 10'!I27 -> 0 | J36: EQUIPO 10
F37: =SUM(F27:F36) -> 0 | G37: =SUM(G27:G36) -> 0 | H37: =SUM(H27:H36) -> 0 | I37: =SUM(I27:I36) -> 0 | J37: TOTAL
F39: MANTENIMIENTO
F40: TOTAL ELEGIBLE EUROPEOS (€) | G40: TOTAL NO ELEGIBLE EUROPEOS (€) | H40: TOTAL MARGINAL (€) | I40: TOTAL AMORTIZACIÓN (€)
F41: ='Equipo 1'!F32 -> 0 | G41: ='Equipo 1'!G32 -> 0 | H41: ='Equipo 1'!H32 -> 0 | I41: ='Equipo 1'!I32 -> 0 | J41: EQUIPO 1
F42: ='Equipo 2'!F32 -> 0 | G42: ='Equipo 2'!G32 -> 0 | H42: ='Equipo 2'!H32 -> 0 | I42: ='Equipo 2'!I32 -> 0 | J42: EQUIPO 2
F43: ='Equipo 3'!F32 -> 0 | G43: ='Equipo 3'!G32 -> 0 | H43: ='Equipo 3'!H32 -> 0 | I43: ='Equipo 3'!I32 -> 0 | J43: EQUIPO 3
F44: ='Equipo 4'!F32 -> 0 | G44: ='Equipo 4'!G32 -> 0 | H44: ='Equipo 4'!H32 -> 0 | I44: ='Equipo 4'!I32 -> 0 | J44: EQUIPO 4
F45: ='Equipo 5'!F32 -> 0 | G45: ='Equipo 5'!G32 -> 0 | H45: ='Equipo 5'!H32 -> 0 | I45: ='Equipo 5'!I32 -> 0 | J45: EQUIPO 5
F46: ='Equipo 6'!F32 -> 0 | G46: ='Equipo 6'!G32 -> 0 | H46: ='Equipo 6'!H32 -> 0 | I46: ='Equipo 6'!I32 -> 0 | J46: EQUIPO 6
F47: ='Equipo 7'!F32 -> 0 | G47: ='Equipo 7'!G32 -> 0 | H47: ='Equipo 7'!H32 -> 0 | I47: ='Equipo 7'!I32 -> 0 | J47: EQUIPO 7
F48: ='Equipo 8'!F32 -> 0 | G48: ='Equipo 8'!G32 -> 0 | H48: ='Equipo 8'!H32 -> 0 | I48: ='Equipo 8'!I32 -> 0 | J48: EQUIPO 8
F49: ='Equipo 9'!F32 -> 0 | G49: ='Equipo 9'!G32 -> 0 | H49: ='Equipo 9'!H32 -> 0 | I49: ='Equipo 9'!I32 -> 0 | J49: EQUIPO 9
F50: ='Equipo 10'!F32 -> 0 | G50: ='Equipo 10'!G32 -> 0 | H50: ='Equipo 10'!H32 -> 0 | I50: ='Equipo 10'!I32 -> 0 | J50: EQUIPO 10
F51: =SUM(F41:F50) -> 0 | G51: =SUM(G41:G50) -> 0 | H51: =SUM(H41:H50) -> 0 | I51: =SUM(I41:I50) -> 0 | J51: TOTAL
F53: ARRANQUE/ENFRIAMIENTO
F54: TOTAL ELEGIBLE EUROPEOS (€) | G54: TOTAL NO ELEGIBLE EUROPEOS (€) | H54: TOTAL MARGINAL (€) | I54: TOTAL AMORTIZACIÓN (€)
F55: ='Equipo 1'!F42 -> 0 | G55: ='Equipo 1'!G42 -> 0 | H55: ='Equipo 1'!H42 -> 0 | I55: ='Equipo 1'!I42 -> 0 | J55: EQUIPO 1
F56: ='Equipo 2'!F42 -> 0 | G56: ='Equipo 2'!G42 -> 0 | H56: ='Equipo 2'!H42 -> 0 | I56: ='Equipo 2'!I42 -> 0 | J56: EQUIPO 2
F57: ='Equipo 3'!F42 -> 0 | G57: ='Equipo 3'!G42 -> 0 | H57: ='Equipo 3'!H42 -> 0 | I57: ='Equipo 3'!I42 -> 0 | J57: EQUIPO 3
F58: ='Equipo 4'!F42 -> 0 | G58: ='Equipo 4'!G42 -> 0 | H58: ='Equipo 4'!H42 -> 0 | I58: ='Equipo 4'!I42 -> 0 | J58: EQUIPO 4
F59: ='Equipo 5'!F42 -> 0 | G59: ='Equipo 5'!G42 -> 0 | H59: ='Equipo 5'!H42 -> 0 | I59: ='Equipo 5'!I42 -> 0 | J59: EQUIPO 5
F60: ='Equipo 6'!F42 -> 0 | G60: ='Equipo 6'!G42 -> 0 | H60: ='Equipo 6'!H42 -> 0 | I60: ='Equipo 6'!I42 -> 0 | J60: EQUIPO 6
F61: ='Equipo 7'!F42 -> 0 | G61: ='Equipo 7'!G42 -> 0 | H61: ='Equipo 7'!H42 -> 0 | I61: ='Equipo 7'!I42 -> 0 | J61: EQUIPO 7
F62: ='Equipo 8'!F42 -> 0 | G62: ='Equipo 8'!G42 -> 0 | H62: ='Equipo 8'!H42 -> 0 | I62: ='Equipo 8'!I42 -> 0 | J62: EQUIPO 8
F63: ='Equipo 9'!F42 -> 0 | G63: ='Equipo 9'!G42 -> 0 | H63: ='Equipo 9'!H42 -> 0 | I63: ='Equipo 9'!I42 -> 0 | J63: EQUIPO 9
F64: ='Equipo 10'!F42 -> 0 | G64: ='Equipo 10'!G42 -> 0 | H64: ='Equipo 10'!H42 -> 0 | I64: ='Equipo 10'!I42 -> 0 | J64: EQUIPO 10
F65: =SUM(F55:F64) -> 0 | G65: =SUM(G55:G64) -> 0 | H65: =SUM(H55:H64) -> 0 | I65: =SUM(I55:I64) -> 0 | J65: TOTAL
F67: CALIBRACIÓN
F68: TOTAL ELEGIBLE EUROPEOS (€) | G68: TOTAL NO ELEGIBLE EUROPEOS (€) | H68: TOTAL MARGINAL (€) | I68: TOTAL AMORTIZACIÓN (€)
F69: ='Equipo 1'!F53 -> 0 | G69: ='Equipo 1'!G53 -> 0 | H69: ='Equipo 1'!H53 -> 0 | I69: ='Equipo 1'!I53 -> 0 | J69: EQUIPO 1
F70: ='Equipo 2'!F53 -> 0 | G70: ='Equipo 2'!G53 -> 0 | H70: ='Equipo 2'!H53 -> 0 | I70: ='Equipo 2'!I53 -> 0 | J70: EQUIPO 2
F71: ='Equipo 3'!F53 -> 0 | G71: ='Equipo 3'!G53 -> 0 | H71: ='Equipo 3'!H53 -> 0 | I71: ='Equipo 3'!I53 -> 0 | J71: EQUIPO 3
F72: ='Equipo 4'!F53 -> 0 | G72: ='Equipo 4'!G53 -> 0 | H72: ='Equipo 4'!H53 -> 0 | I72: ='Equipo 4'!I53 -> 0 | J72: EQUIPO 4
F73: ='Equipo 5'!F53 -> 0 | G73: ='Equipo 5'!G53 -> 0 | H73: ='Equipo 5'!H53 -> 0 | I73: ='Equipo 5'!I53 -> 0 | J73: EQUIPO 5
F74: ='Equipo 6'!F53 -> 0 | G74: ='Equipo 6'!G53 -> 0 | H74: ='Equipo 6'!H53 -> 0 | I74: ='Equipo 6'!I53 -> 0 | J74: EQUIPO 6
F75: ='Equipo 7'!F53 -> 0 | G75: ='Equipo 7'!G53 -> 0 | H75: ='Equipo 7'!H53 -> 0 | I75: ='Equipo 7'!I53 -> 0 | J75: EQUIPO 7
F76: ='Equipo 8'!F53 -> 0 | G76: ='Equipo 8'!G53 -> 0 | H76: ='Equipo 8'!H53 -> 0 | I76: ='Equipo 8'!I53 -> 0 | J76: EQUIPO 8
F77: ='Equipo 9'!F53 -> 0 | G77: ='Equipo 9'!G53 -> 0 | H77: ='Equipo 9'!H53 -> 0 | I77: ='Equipo 9'!I53 -> 0 | J77: EQUIPO 9
F78: ='Equipo 10'!F53 -> 0 | G78: ='Equipo 10'!G53 -> 0 | H78: ='Equipo 10'!H53 -> 0 | I78: ='Equipo 10'!I53 -> 0 | J78: EQUIPO 10
F79: =SUM(F69:F78) -> 0 | G79: =SUM(G69:G78) -> 0 | H79: =SUM(H69:H78) -> 0 | I79: =SUM(I69:I78) -> 0 | J79: TOTAL

Sheet Otros
A2: OTROS (por UMC)
A4: UMC (€) | B4: =IF('Datos generales'!B11:C11="(Campo desplegable)","Indicar en la hoja de 'Datos generales'",'Datos generales'!B11:C11) -> Indicar en la hoja de 'Datos generales'
B6: DESCRIPCIÓN DE LA UTILIZACIÓN
A9: OTROS: FUNGIBLES/FLUIDOS | B9: Información para el cálculo del coste | G9: ELEGIBLE EUROPEOS | H9: NO ELEGIBLE EUROPEOS | I9: MARGINAL | J9: AMORTIZACIÓN
A10: Otros fungibles/Fluidos 1 | B10: Incluir los costes - IMPORTE SIN IVA (€): -Contables, número de fungibles o grupos de fungibles por coste unidad/grupo según facturas/mercado | E10: 0 | G10: X | I10: X
B11: Breve descripción de fungibles/fluidos utilizados ->
B12: Incluir los costes - IMPORTE SIN IVA (€): No contables (continuos), medida de consumo por coste UMC según facturas/mercado | E12: 0 | G12: X | I12: X
B13: Breve descripción de fungibles/fluidos utilizados ->
B14: Incluir los costes - IMPORTE SIN IVA (€): No contables (continuos), estimación de consumo por coste UMC según factura o precio de mercado | E14: 0 | H14: X | I14: X
B15: Breve descripción de fungibles/fluidos utilizados ->
A16: Otros fungibles/Fluidos 2 | B16: Incluir los costes - IMPORTE SIN IVA (€): -Contables, número de fungibles o grupos de fungibles por coste unidad/grupo según facturas/mercado | E16: 0 | G16: X | I16: X
B17: Breve descripción de fungibles/fluidos utilizados ->
B18: Incluir los costes - IMPORTE SIN IVA (€): No contables (continuos), medida de consumo por coste UMC según facturas/mercado | E18: 0 | G18: X | I18: X
B19: Breve descripción de fungibles/fluidos utilizados ->
B20: Incluir los costes - IMPORTE SIN IVA (€): No contables (continuos), estimación de consumo por coste UMC según factura o precio de mercado | E20: 0 | H20: X | I20: X
B21: Breve descripción de fungibles/fluidos utilizados ->
A22: Otros fungibles/Fluidos 3 | B22: Incluir los costes - IMPORTE SIN IVA (€): -Contables, número de fungibles o grupos de fungibles por coste unidad/grupo según facturas/mercado | E22: 0 | G22: X | I22: X
B23: Breve descripción de fungibles/fluidos utilizados ->
B24: Incluir los costes - IMPORTE SIN IVA (€): No contables (continuos), medida de consumo por coste UMC según facturas/mercado | E24: 0 | G24: X | I24: X
B25: Breve descripción de fungibles/fluidos utilizados ->
B26: Incluir los costes - IMPORTE SIN IVA (€): No contables (continuos), estimación de consumo por coste UMC según factura o precio de mercado | E26: 0 | H26: X | I26: X
B27: Breve descripción de fungibles/fluidos utilizados ->
A28: Otros fungibles/Fluidos 4 | B28: Incluir los costes - IMPORTE SIN IVA (€): -Contables, número de fungibles o grupos de fungibles por coste unidad/grupo según facturas/mercado | E28: 0 | G28: X | I28: X
B29: Breve descripción de fungibles/fluidos utilizados ->
B30: Incluir los costes - IMPORTE SIN IVA (€): No contables (continuos), medida de consumo por coste UMC según facturas/mercado | E30: 0 | G30: X | I30: X
B31: Breve descripción de fungibles/fluidos utilizados ->
B32: Incluir los costes - IMPORTE SIN IVA (€): No contables (continuos), estimación de consumo por coste UMC según factura o precio de mercado | E32: 0 | H32: X | I32: X
B33: Breve descripción de fungibles/fluidos utilizados ->
A34: COSTE TOTAL (UMC) OTROS FUNGIBLES/FLUIDOS | B34: → | E34: =SUM(E10,E12,E14,E16,E18,E20,E22,E24,E26,E28,E30,E32) -> 0 | G34: =SUMIF(G10:G32,"X",$E$10:$E$32) -> 0 | H34: =SUMIF(H10:H32,"X",$E$10:$E$32) -> 0 | I34: =SUMIF(I10:I32,"X",$E$10:$E$32) -> 0 | J34: =SUMIF(J10:J32,"X",$E$10:$E$32) -> 0
A36: OTROS: SOFTWARE | B36: Información para el cálculo del coste
A37: Software 1 | B37: Rellenar en caso de software en periodo de amortización
A38: Amortización de las licencias y actualizaciones de programas y aplicaciones utilizados, adquiridas de forma independiente a los equipos y que sean disociables a estos (por ejemplo una actualización o nuevo software necesario para la prestación. Periodo amortización: A=3) | B38: Nombre y breve descripción del software
B39: Fecha de adquisición | E39: dd/mm/aaaa
B40: Valor de adquisición - IMPORTE SIN IVA (€) | E40: 0
B41: Subvención de la UE - IMPORTE SIN IVA (€) | E41: 0
B42: Tiempo de utilización anual del software en horas | E42: 1
B43: Tiempo utilizado durante una UMC en hora/s y fracción | E43: 0
B44: Costes imputables - IMPORTE SIN IVA (€) | E44: =((E40-E41)/3)*(E43/E42) -> 0
A45: Software 2 | B45: Rellenar en caso de software en periodo de amortización
A46: Amortización de las licencias y actualizaciones de programas y aplicaciones utilizados, adquiridas de forma independiente a los equipos y que sean disociables a estos (por ejemplo una actualización o nuevo software necesario para la prestación. Periodo amortización: A=3) | B46: Nombre y breve descripción del software
B47: Fecha de adquisición | E47: dd/mm/aaaa
B48: Valor de adquisición - IMPORTE SIN IVA (€) | E48: 0
B49: Subvención de la UE - IMPORTE SIN IVA (€) | E49: 0
B50: Tiempo de utilización anual del software en horas | E50: 1
B51: Tiempo utilizado durante una UMC en hora/s y fracción | E51: 0
B52: Costes imputables - IMPORTE SIN IVA (€) | E52: =((E48-E49)/3)*(E51/E50) -> 0
A53: COSTE TOTAL (UMC) SOFTWARE | B53: → | E53: =SUM(E44,E52) -> 0 | G53: X
G54: =SUMIF(G53,"X",$E$53) -> 0 | H54: =SUMIF(H53,"X",$E$53) -> 0 | I54: =SUMIF(I53,"X",$E$53) -> 0 | J54: =SUMIF(J53,"X",$E$53) -> 0
A55: OTROS: SUBCONTRATACIONES | B55: Información para el cálculo del coste | E55: IMPORTE SIN IVA (€)
A56: Subcontratación externa 1 (indicar el importe correspondiente a la UMC) | B56: Breve descripción -> | E56: 0
A57: Subcontratación externa 2 (indicar el importe correspondiente a la UMC) | B57: Breve descripción -> | E57: 0
A58: COSTE TOTAL (UMC) SUBCONTRATACIONES | B58: → | E58: =SUM(E56:E57) -> 0 | G58: X | I58: X
G59: =SUMIF(G58,"X",$E$58) -> 0 | H59: =SUMIF(H58,"X",$E$58) -> 0 | I59: =SUMIF(I58,"X",$E$58) -> 0 | J59: =SUMIF(J58,"X",$E$58) -> 0
A60: OTROS: CERTIFICACIONES | B60: Información para el cálculo del coste
A61: Certificación/acreditación del equipo/técnica/proceso 1 | B61: Nombre y breve descripción de la certificación/acreditación
B62: Duración del uso del equipo, técnica, proceso certificado/acreditado en hora y fracción | E62: 0
B63: Coste anual de la certificación/acreditación del recurso - IMPORTE SIN IVA (€) | E63: 0
B64: COSTE TOTAL CERTIFICACIÓN 1 - IMPORTE SIN IVA (€) | E64: =(E63/8760)*E62 -> 0
A65: Certificación/acreditación del equipo/técnica/proceso 2 | B65: Nombre y breve descripción de la certificación/acreditación
B66: Duración del uso del equipo, técnica, proceso certificado/acreditado en hora y fracción | E66: 0
B67: Coste anual de la certificación/acreditación del recurso - IMPORTE SIN IVA (€) | E67: 0
B68: COSTE TOTAL CERTIFICACIÓN 2 - IMPORTE SIN IVA (€) | E68: =(E67/8760)*E66 -> 0
A69: COSTE TOTAL (UMC) CERTIFICACIONES | B69: → | E69: =SUM(E64,E68) -> 0 | H69: X
G70: =SUMIF(G69,"X",$E$69) -> 0 | H70: =SUMIF(H69,"X",$E$69) -> 0 | I70: =SUMIF(I69,"X",$E$69) -> 0 | J70: =SUMIF(J69,"X",$E$69) -> 0
B71: COSTE TOTAL (UMC) OTROS | E71: TOTAL IMPORTE SIN IVA (€) | G71: TOTAL ELEGIBLE EUROPEOS (€) | H71: TOTAL NO ELEGIBLE EUROPEOS (€) | I71: TOTAL MARGINAL (€) | J71: TOTAL AMORTIZACIÓN (€)
B72: Suma del coste total para otros, implicado en el desarrollo de la variante | E72: =SUM(E34,E53,E58,E69) -> 0 | G72: =SUMIF(G10:G69,"X",$E$10:$E$69) -> 0 | H72: =SUMIF(H10:H69,"X",$E$10:$E$69) -> 0 | I72: =SUMIF(I10:I69,"X",$E$10:$E$69) -> 0 | J72: =SUMIF(J10:J69,"X",$E$10:$E$69) -> 0

Sheet Equipo 1
A2: EQUIPO 1 (por UMC)
A4: UMC (€) | B4: =IF('Datos generales'!B11:C11="(Campo desplegable)","Indicar en la hoja de 'Datos generales'",'Datos generales'!B11:C11) -> Indicar en la hoja de 'Datos generales'
A6: =IF(Equipamiento!B10="Campo rellenable de descripción del equipo","Campo automático",Equipamiento!B10) -> Campo automático
A7: DATOS DE LA UTILIZACIÓN | B7: Información para el cálculo del coste
A8: Tipo de equipamiento | B8: (Campo desplegable)
A9: Indique si el equipo está amortizado | B9: (Campo desplegable)
A10: Periodo de amortización | B10: =IF(B8="(Campo desplegable)","Campo automático",VLOOKUP(B8,Referencias!A32:B33,2,FALSE)) -> Campo automático
A11: Tiempos de uso del equipo 1 | B11: Tiempo de utilización anual del equipo en horas | D11: 1
B12: Tiempo utilizado durante una UMC en hora/s y fracción | D12: 0
A13: UTILIZACIÓN DEL EQUIPO 1
A14: Energía | B14: Indique si la energía es: -Medida con un contador y valorada con las tarifas del contrato de suministro vigente -Estimada mediante facturas | D14: (Campo desplegable) | F14: ELEGIBLE EUROPEOS | G14: NO ELEGIBLE EUROPEOS | H14: MARGINAL | I14: AMORTIZACIÓN
B15: Coste de energía por UMC - IMPORTE SIN IVA (€) | D15: 0 | F15: =IF($D14="Medida con un contador","X","") | G15: =IF($D14="Estimada mediante facturas","X","") | H15: X
A16: Fungibles/Fluidos | B16: Incluir los costes - IMPORTE SIN IVA (€): Contables, número de fungibles o grupos de fungibles por coste unidad/grupo según facturas/mercado | D16: 0 | F16: X | H16: X
B17: Breve descripción de fungibles/fluidos utilizados ->
B18: Incluir los costes - IMPORTE SIN IVA (€): No contables (continuos), medida de consumo por coste UMC según facturas/mercado | D18: 0 | F18: X | H18: X
B19: Breve descripción de fungibles/fluidos utilizados ->
B20: Incluir los costes - IMPORTE SIN IVA (€): No contables (continuos), estimación de consumo por coste UMC según factura o precio de mercado | D20: 0 | G20: X | H20: X
B21: Breve descripción de fungibles/fluidos utilizados ->
A22: Amortización (si la antigüedad es inferior al periodo de amortización) | B22: Fecha de adquisición | D22: dd/mm/aaaa
B23: Valor de adquisición - IMPORTE SIN IVA (€) | D23: 0
B24: Subvención de la UE - IMPORTE SIN IVA (€) | D24: 0
B25: COSTES DE AMORTIZACIÓN ELEGIBLES PARA PROYECTOS DEL PROGRAMA MARCO POR UMC - IMPORTE SIN IVA (€) | D25: =IF(OR(B9="SÍ",B9="(Campo desplegable)"),0,((D23-D24)/B10)*(D12/D11)) -> 0 | F25: X | I25: X
B26: DIFERENCIA entre el coste de la amortización contable CSIC, C = (V/A)x t/T, donde V es el precio TOTAL de adquisición y A el periodo de amortización CSIC (véase tabla "Periodos amortización CSIC"), con el valor consignado en la casilla del coste elegible (el valor podría resultar negativo, como una corrección a la amortización acelerada que impone H2020). - IMPORTE SIN IVA (€) | D26: =IF(OR(B9="SÍ",B9="(Campo desplegable)"),0,((D23/B10)*(D12/D11))-D25) -> 0 | G26: X | I26: X
A27: COSTE TOTAL (UMC) UTILIZACIÓN DEL EQUIPO 1 | B27: → | D27: =SUM(D15,D16,D18,D20,D25,D26) -> 0 | F27: =SUMIF(F15:F26,"X",$D$15:$D$26) -> 0 | G27: =SUMIF(G15:G26,"X",$D$15:$D$26) -> 0 | H27: =SUMIF(H15:H26,"X",$D$15:$D$26) -> 0 | I27: =SUMIF(I15:I26,"X",$D$15:$D$26) -> 0
A29: MANTENIMIENTO EQUIPO 1
A30: Mantenimiento del Equipo 1 (incluyendo calibraciones preprogramadas) | B30: Coste anual de reparación y mantenimiento (o media del coste de los últimos cinco años) - IMPORTE SIN IVA (€) | D30: 0
A31: COSTE TOTAL (UMC) MANTENIMIENTO EQUIPO 1 IMPORTE SIN IVA (€) | B31: → | D31: =(D30*D12/D11) -> 0 | G31: X
F32: =SUMIF(F30:F31,"X",$D$30:$D$31) -> 0 | G32: =SUMIF(G30:G31,"X",$D$30:$D$31) -> 0 | H32: =SUMIF(H30:H31,"X",$D$30:$D$31) -> 0 | I32: =SUMIF(I30:I31,"X",$D$30:$D$31) -> 0
A33: ARRANQUE/ENFRIAMIENTO EQUIPO 1
A34: Energía | B34: Energía por arranque/enfriamiento - IMPORTE SIN IVA (€) | D34: 0 | G34: X | H34: X
A35: Fungibles/Fluidos | B35: Fungibles/Fluidos por arranque/enfriamiento - IMPORTE SIN IVA (€) | D35: 0 | G35: X | H35: X
B36: Breve descripción de fungibles/fluidos utilizados ->
A37: Amortización | B37: Rellenar en caso de equipamiento en periodo de amortización
B38: Nº medio de UMC por arranque/enfriamiento | D38: 1
B39: Tiempo de arranque/enfriamiento en hora/s y fracción | D39: 0
B40: COSTES DE AMORTIZACIÓN NO ELEGIBLES PARA PROYECTOS DEL PROGRAMA MARCO - IMPORTE SIN IVA (€) | D40: =IF(OR(B9="SÍ",B9="(Campo desplegable)"),0,(D23/B10)*(D39/D11)) -> 0
B41: Amortización asociada al tiempo de arranque/enfriamiento por UMC - IMPORTE SIN IVA (€) | D41: =D40/D38 -> 0 | G41: X | I41: X
A42: COSTE TOTAL (UMC) ARRANQUE/ENFRIAMIENTO EQUIPO 1 IMPORTE SIN IVA (€) | B42: → | D42: =SUM(D34,D35,D41) -> 0 | F42: =SUMIF(F34:F41,"X",$D$34:$D$41) -> 0 | G42: =SUMIF(G34:G41,"X",$D$34:$D$41) -> 0 | H42: =SUMIF(H34:H41,"X",$D$34:$D$41) -> 0 | I42: =SUMIF(I34:I41,"X",$D$34:$D$41) -> 0
A44: CALIBRACIÓN INTERMEDIA DEL EQUIPO 1
A45: Energía | B45: Energía por calibración - IMPORTE SIN IVA (€) | D45: 0 | G45: X | H45: X
A46: Fungibles/Fluidos | B46: Fungibles/Fluidos por calibración - IMPORTE SIN IVA (€) | D46: 0 | G46: X | H46: X
B47: Breve descripción de fungibles/fluidos utilizados ->
A48: Amortización | B48: Rellenar en caso de equipamiento en periodo de amortización
B49: Nº medio de UMC por calibración | D49: 1
B50: Tiempo de la calibración en hora/s y fracción | D50: 0
B51: COSTES DE AMORTIZACIÓN NO ELEGIBLES PARA PROYECTOS DEL PROGRAMA MARCO - IMPORTE SIN IVA (€) | D51: =IF(OR(B9="SÍ",B9="(Campo desplegable)"),0,(D23/B10)*(D50/D11)) -> 0
B52: Amortización de la calibración por UMC - IMPORTE SIN IVA (€) | D52: =D51/D49 -> 0 | G52: X | I52: X
A53: COSTE TOTAL (UMC) CALIBRACIÓN INTERMEDIA DEL EQUIPO 1 (durante el transcurso de un grupo de prestaciones) IMPORTE SIN IVA (€) | B53: → | D53: =SUM(D45,D46,D52) -> 0 | F53: =SUMIF(F45:F52,"X",$D$45:$D$52) -> 0 | G53: =SUMIF(G45:G52,"X",$D$45:$D$52) -> 0 | H53: =SUMIF(H45:H52,"X",$D$45:$D$52) -> 0 | I53: =SUMIF(I45:I52,"X",$D$45:$D$52) -> 0
B55: COSTE TOTAL (UMC) EQUIPO 1 | D55: TOTAL IMPORTE SIN IVA (€) | F55: TOTAL ELEGIBLE EUROPEOS (€) | G55: TOTAL NO ELEGIBLE EUROPEOS (€) | H55: TOTAL MARGINAL (€) | I55: TOTAL AMORTIZACIÓN (€)
A56: VOLVER A EQUIPAMIENTO | B56: Suma del coste total del equipo 1 implicado en el desarrollo por UMC | D56: =SUM(D27,D31,D42,D53) -> 0 | F56: =SUMIF(F15:F52,"X",$D$15:$D$52) -> 0 | G56: =SUMIF(G15:G52,"X",$D$15:$D$52) -> 0 | H56: =SUMIF(H15:H52,"X",$D$15:$D$52) -> 0 | I56: =SUMIF(I15:I52,"X",$D$15:$D$52) -> 0

Sheet Equipo 2
A2: EQUIPO 2 (por UMC)
A4: UMC (€) | B4: =IF('Datos generales'!B11:C11="(Campo desplegable)","Indicar en la hoja de 'Datos generales'",'Datos generales'!B11:C11) -> Indicar en la hoja de 'Datos generales'
A6: =IF(Equipamiento!B11="Campo rellenable de descripción del equipo","Campo automático",Equipamiento!B11) -> Campo automático
A7: DATOS DE LA UTILIZACIÓN | B7: Información para el cálculo del coste
A8: Tipo de equipamiento | B8: (Campo desplegable)
A9: Indique si el equipo está amortizado | B9: (Campo desplegable)
A10: Periodo de amortización | B10: =IF(B8="(Campo desplegable)","Campo automático",VLOOKUP(B8,Referencias!A32:B33,2,FALSE)) -> Campo automático
A11: Tiempos de uso del equipo 2 | B11: Tiempo de utilización anual del equipo en horas | D11: 1
B12: Tiempo utilizado durante una UMC en hora/s y fracción | D12: 0
A13: UTILIZACIÓN DEL EQUIPO 2
A14: Energía | B14: Indique si la energía es: -Medida con un contador y valorada con las tarifas del contrato de suministro vigente -Estimada mediante facturas | D14: (Campo desplegable) | F14: ELEGIBLE EUROPEOS | G14: NO ELEGIBLE EUROPEOS | H14: MARGINAL | I14: AMORTIZACIÓN
B15: Coste de energía por UMC - IMPORTE SIN IVA (€) | D15: 0 | F15: =IF($D14="Medida con un contador","X","") | G15: =IF($D14="Estimada mediante facturas","X","") | H15: X
A16: Fungibles/Fluidos | B16: Incluir los costes - IMPORTE SIN IVA (€): Contables, número de fungibles o grupos de fungibles por coste unidad/grupo según facturas/mercado | D16: 0 | F16: X | H16: X
B17: Breve descripción de fungibles/fluidos utilizados ->
B18: Incluir los costes - IMPORTE SIN IVA (€): No contables (continuos), medida de consumo por coste UMC según facturas/mercado | D18: 0 | F18: X | H18: X
B19: Breve descripción de fungibles/fluidos utilizados ->
B20: Incluir los costes - IMPORTE SIN IVA (€): No contables (continuos), estimación de consumo por coste UMC según factura o precio de mercado | D20: 0 | G20: X | H20: X
B21: Breve descripción de fungibles/fluidos utilizados ->
A22: Amortización (si la antigüedad es inferior al periodo de amortización) | B22: Fecha de adquisición | D22: dd/mm/aaaa
B23: Valor de adquisición - IMPORTE SIN IVA (€) | D23: 0
B24: Subvención de la UE - IMPORTE SIN IVA (€) | D24: 0
B25: COSTES DE AMORTIZACIÓN ELEGIBLES PARA PROYECTOS DEL PROGRAMA MARCO POR UMC - IMPORTE SIN IVA (€) | D25: =IF(OR(B9="SÍ",B9="(Campo desplegable)"),0,((D23-D24)/B10)*(D12/D11)) -> 0 | F25: X | I25: X
B26: DIFERENCIA entre el coste de la amortización contable CSIC, C = (V/A)x t/T, donde V es el precio TOTAL de adquisición y A el periodo de amortización CSIC (véase tabla "Periodos amortización CSIC"), con el valor consignado en la casilla del coste elegible (el valor podría resultar negativo, como una corrección a la amortización acelerada que impone H2020). - IMPORTE SIN IVA (€) | D26: =IF(OR(B9="SÍ",B9="(Campo desplegable)"),0,((D23/B10)*(D12/D11))-D25) -> 0 | G26: X | I26: X
A27: COSTE TOTAL (UMC) UTILIZACIÓN DEL EQUIPO 2 | B27: → | D27: =SUM(D15,D16,D18,D20,D25,D26) -> 0 | F27: =SUMIF(F15:F26,"X",$D$15:$D$26) -> 0 | G27: =SUMIF(G15:G26,"X",$D$15:$D$26) -> 0 | H27: =SUMIF(H15:H26,"X",$D$15:$D$26) -> 0 | I27: =SUMIF(I15:I26,"X",$D$15:$D$26) -> 0
A29: MANTENIMIENTO EQUIPO 2
A30: Mantenimiento del equipo 2 (incluyendo calibraciones preprogramadas) | B30: Coste anual de reparación y mantenimiento (o media del coste de los últimos cinco años) - IMPORTE SIN IVA (€) | D30: 0
A31: COSTE TOTAL (UMC) MANTENIMIENTO equipo 2 IMPORTE SIN IVA (€) | B31: → | D31: =(D30*D12/D11) -> 0 | G31: X
F32: =SUMIF(F30:F31,"X",$D$30:$D$31) -> 0 | G32: =SUMIF(G30:G31,"X",$D$30:$D$31) -> 0 | H32: =SUMIF(H30:H31,"X",$D$30:$D$31) -> 0 | I32: =SUMIF(I30:I31,"X",$D$30:$D$31) -> 0
A33: ARRANQUE/ENFRIAMIENTO EQUIPO 2
A34: Energía | B34: Energía por arranque/enfriamiento - IMPORTE SIN IVA (€) | D34: 0 | G34: X | H34: X
A35: Fungibles/Fluidos | B35: Fungibles/Fluidos por arranque/enfriamiento - IMPORTE SIN IVA (€) | D35: 0 | G35: X | H35: X
B36: Breve descripción de fungibles/fluidos utilizados ->
A37: Amortización | B37: Rellenar en caso de equipamiento en periodo de amortización
B38: Nº medio de UMC por arranque/enfriamiento | D38: 1
B39: Tiempo de arranque/enfriamiento en hora/s y fracción | D39: 0
B40: COSTES DE AMORTIZACIÓN NO ELEGIBLES PARA PROYECTOS DEL PROGRAMA MARCO - IMPORTE SIN IVA (€) | D40: =IF(OR(B9="SÍ",B9="(Campo desplegable)"),0,(D23/B10)*(D39/D11)) -> 0
B41: Amortización asociada al tiempo de arranque/enfriamiento por UMC - IMPORTE SIN IVA (€) | D41: =D40/D38 -> 0 | G41: X | I41: X
A42: COSTE TOTAL (UMC) ARRANQUE/ENFRIAMIENTO EQUIPO 2 IMPORTE SIN IVA (€) | B42: → | D42: =SUM(D34,D35,D41) -> 0 | F42: =SUMIF(F34:F41,"X",$D$34:$D$41) -> 0 | G42: =SUMIF(G34:G41,"X",$D$34:$D$41) -> 0 | H42: =SUMIF(H34:H41,"X",$D$34:$D$41) -> 0 | I42: =SUMIF(I34:I41,"X",$D$34:$D$41) -> 0
A44: CALIBRACIÓN INTERMEDIA DEL EQUIPO 2
A45: Energía | B45: Energía por calibración - IMPORTE SIN IVA (€) | D45: 0 | G45: X | H45: X
A46: Fungibles/Fluidos | B46: Fungibles/Fluidos por calibración - IMPORTE SIN IVA (€) | D46: 0 | G46: X | H46: X
B47: Breve descripción de fungibles/fluidos utilizados ->
A48: Amortización | B48: Rellenar en caso de equipamiento en periodo de amortización
B49: Nº medio de UMC por calibración | D49: 1
B50: Tiempo de la calibración en hora/s y fracción | D50: 0
B51: COSTES DE AMORTIZACIÓN NO ELEGIBLES PARA PROYECTOS DEL PROGRAMA MARCO - IMPORTE SIN IVA (€) | D51: =IF(OR(B9="SÍ",B9="(Campo desplegable)"),0,(D23/B10)*(D50/D11)) -> 0
B52: Amortización de la calibración por UMC - IMPORTE SIN IVA (€) | D52: =D51/D49 -> 0 | G52: X | I52: X
A53: COSTE TOTAL (UMC) CALIBRACIÓN INTERMEDIA DEL EQUIPO 2 (durante el transcurso de un grupo de prestaciones) IMPORTE SIN IVA (€) | B53: → | D53: =SUM(D45,D46,D52) -> 0 | F53: =SUMIF(F45:F52,"X",$D$45:$D$52) -> 0 | G53: =SUMIF(G45:G52,"X",$D$45:$D$52) -> 0 | H53: =SUMIF(H45:H52,"X",$D$45:$D$52) -> 0 | I53: =SUMIF(I45:I52,"X",$D$45:$D$52) -> 0
B55: COSTE TOTAL (UMC) EQUIPO 2 | D55: TOTAL IMPORTE SIN IVA (€) | F55: TOTAL ELEGIBLE EUROPEOS (€) | G55: TOTAL NO ELEGIBLE EUROPEOS (€) | H55: TOTAL MARGINAL (€) | I55: TOTAL AMORTIZACIÓN (€)
A56: VOLVER A EQUIPAMIENTO | B56: Suma del coste total del equipo 2 implicado en el desarrollo por UMC | D56: =SUM(D27,D31,D42,D53) -> 0 | F56: =SUMIF(F15:F52,"X",$D$15:$D$52) -> 0 | G56: =SUMIF(G15:G52,"X",$D$15:$D$52) -> 0 | H56: =SUMIF(H15:H52,"X",$D$15:$D$52) -> 0 | I56: =SUMIF(I15:I52,"X",$D$15:$D$52) -> 0

Sheet Equipo 3
A2: EQUIPO 3 (por UMC)
A4: UMC (€) | B4: =IF('Datos generales'!B11:C11="(Campo desplegable)","Indicar en la hoja de 'Datos generales'",'Datos generales'!B11:C11) -> Indicar en la hoja de 'Datos generales'
A6: =IF(Equipamiento!B12="Campo rellenable de descripción del equipo","Campo automático",Equipamiento!B12) -> Campo automático
A7: DATOS DE LA UTILIZACIÓN | B7: Información para el cálculo del coste
A8: Tipo de equipamiento | B8: (Campo desplegable)
A9: Indique si el equipo está amortizado | B9: (Campo desplegable)
A10: Periodo de amortización | B10: =IF(B8="(Campo desplegable)","Campo automático",VLOOKUP(B8,Referencias!A32:B33,2,FALSE)) -> Campo automático
A11: Tiempos de uso del equipo 3 | B11: Tiempo de utilización anual del equipo en horas | D11: 1
B12: Tiempo utilizado durante una UMC en hora/s y fracción | D12: 0
A13: UTILIZACIÓN DEL EQUIPO 3
A14: Energía | B14: Indique si la energía es: -Medida con un contador y valorada con las tarifas del contrato de suministro vigente -Estimada mediante facturas | D14: (Campo desplegable) | F14: ELEGIBLE EUROPEOS | G14: NO ELEGIBLE EUROPEOS | H14: MARGINAL | I14: AMORTIZACIÓN
B15: Coste de energía por UMC - IMPORTE SIN IVA (€) | D15: 0 | F15: =IF($D14="Medida con un contador","X","") | G15: =IF($D14="Estimada mediante facturas","X","") | H15: X
A16: Fungibles/Fluidos | B16: Incluir los costes - IMPORTE SIN IVA (€): Contables, número de fungibles o grupos de fungibles por coste unidad/grupo según facturas/mercado | D16: 0 | F16: X | H16: X
B17: Breve descripción de fungibles/fluidos utilizados ->
B18: Incluir los costes - IMPORTE SIN IVA (€): No contables (continuos), medida de consumo por coste UMC según facturas/mercado | D18: 0 | F18: X | H18: X
B19: Breve descripción de fungibles/fluidos utilizados ->
B20: Incluir los costes - IMPORTE SIN IVA (€): No contables (continuos), estimación de consumo por coste UMC según factura o precio de mercado | D20: 0 | G20: X | H20: X
B21: Breve descripción de fungibles/fluidos utilizados ->
A22: Amortización (si la antigüedad es inferior al periodo de amortización) | B22: Fecha de adquisición | D22: dd/mm/aaaa
B23: Valor de adquisición - IMPORTE SIN IVA (€) | D23: 0
B24: Subvención de la UE - IMPORTE SIN IVA (€) | D24: 0
B25: COSTES DE AMORTIZACIÓN ELEGIBLES PARA PROYECTOS DEL PROGRAMA MARCO POR UMC - IMPORTE SIN IVA (€) | D25: =IF(OR(B9="SÍ",B9="(Campo desplegable)"),0,((D23-D24)/B10)*(D12/D11)) -> 0 | F25: X | I25: X
B26: DIFERENCIA entre el coste de la amortización contable CSIC, C = (V/A)x t/T, donde V es el precio TOTAL de adquisición y A el periodo de amortización CSIC (véase tabla "Periodos amortización CSIC"), con el valor consignado en la casilla del coste elegible (el valor podría resultar negativo, como una corrección a la amortización acelerada que impone H2020). - IMPORTE SIN IVA (€) | D26: =IF(OR(B9="SÍ",B9="(Campo desplegable)"),0,((D23/B10)*(D12/D11))-D25) -> 0 | G26: X | I26: X
A27: COSTE TOTAL (UMC) UTILIZACIÓN DEL EQUIPO 3 | B27: → | D27: =SUM(D15,D16,D18,D20,D25,D26) -> 0 | F27: =SUMIF(F15:F26,"X",$D$15:$D$26) -> 0 | G27: =SUMIF(G15:G26,"X",$D$15:$D$26) -> 0 | H27: =SUMIF(H15:H26,"X",$D$15:$D$26) -> 0 | I27: =SUMIF(I15:I26,"X",$D$15:$D$26) -> 0
A29: MANTENIMIENTO EQUIPO 3
A30: Mantenimiento del equipo 3 (incluyendo calibraciones preprogramadas) | B30: Coste anual de reparación y mantenimiento (o media del coste de los últimos cinco años) - IMPORTE SIN IVA (€) | D30: 0
A31: COSTE TOTAL (UMC) MANTENIMIENTO EQUIPO 3 IMPORTE SIN IVA (€) | B31: → | D31: =(D30*D12/D11) -> 0 | G31: X
F32: =SUMIF(F30:F31,"X",$D$30:$D$31) -> 0 | G32: =SUMIF(G30:G31,"X",$D$30:$D$31) -> 0 | H32: =SUMIF(H30:H31,"X",$D$30:$D$31) -> 0 | I32: =SUMIF(I30:I31,"X",$D$30:$D$31) -> 0
A33: ARRANQUE/ENFRIAMIENTO EQUIPO 3
A34: Energía | B34: Energía por arranque/enfriamiento - IMPORTE SIN IVA (€) | D34: 0 | G34: X | H34: X
A35: Fungibles/Fluidos | B35: Fungibles/Fluidos por arranque/enfriamiento - IMPORTE SIN IVA (€) | D35: 0 | G35: X | H35: X
B36: Breve descripción de fungibles/fluidos utilizados ->
A37: Amortización | B37: Rellenar en caso de equipamiento en periodo de amortización
B38: Nº medio de UMC por arranque/enfriamiento | D38: 1
B39: Tiempo de arranque/enfriamiento en hora/s y fracción | D39: 0
B40: COSTES DE AMORTIZACIÓN NO ELEGIBLES PARA PROYECTOS DEL PROGRAMA MARCO - IMPORTE SIN IVA (€) | D40: =IF(OR(B9="SÍ",B9="(Campo desplegable)"),0,(D23/B10)*(D39/D11)) -> 0
B41: Amortización asociada al tiempo de arranque/enfriamiento por UMC - IMPORTE SIN IVA (€) | D41: =D40/D38 -> 0 | G41: X | I41: X
A42: COSTE TOTAL (UMC) ARRANQUE/ENFRIAMIENTO EQUIPO 3 IMPORTE SIN IVA (€) | B42: → | D42: =SUM(D34,D35,D41) -> 0 | F42: =SUMIF(F34:F41,"X",$D$34:$D$41) -> 0 | G42: =SUMIF(G34:G41,"X",$D$34:$D$41) -> 0 | H42: =SUMIF(H34:H41,"X",$D$34:$D$41) -> 0 | I42: =SUMIF(I34:I41,"X",$D$34:$D$41) -> 0
A44: CALIBRACIÓN INTERMEDIA DEL EQUIPO 3
A45: Energía | B45: Energía por calibración - IMPORTE SIN IVA (€) | D45: 0 | G45: X | H45: X
A46: Fungibles/Fluidos | B46: Fungibles/Fluidos por calibración - IMPORTE SIN IVA (€) | D46: 0 | G46: X | H46: X
B47: Breve descripción de fungibles/fluidos utilizados ->
A48: Amortización | B48: Rellenar en caso de equipamiento en periodo de amortización
B49: Nº medio de UMC por calibración | D49: 1
B50: Tiempo de la calibración en hora/s y fracción | D50: 0
B51: COSTES DE AMORTIZACIÓN NO ELEGIBLES PARA PROYECTOS DEL PROGRAMA MARCO - IMPORTE SIN IVA (€) | D51: =IF(OR(B9="SÍ",B9="(Campo desplegable)"),0,(D23/B10)*(D50/D11)) -> 0
B52: Amortización de la calibración por UMC - IMPORTE SIN IVA (€) | D52: =D51/D49 -> 0 | G52: X | I52: X
A53: COSTE TOTAL (UMC) CALIBRACIÓN INTERMEDIA DEL EQUIPO 3 (durante el transcurso de un grupo de prestaciones) IMPORTE SIN IVA (€) | B53: → | D53: =SUM(D45,D46,D52) -> 0 | F53: =SUMIF(F45:F52,"X",$D$45:$D$52) -> 0 | G53: =SUMIF(G45:G52,"X",$D$45:$D$52) -> 0 | H53: =SUMIF(H45:H52,"X",$D$45:$D$52) -> 0 | I53: =SUMIF(I45:I52,"X",$D$45:$D$52) -> 0
B55: COSTE TOTAL (UMC) EQUIPO 3 | D55: TOTAL IMPORTE SIN IVA (€) | F55: TOTAL ELEGIBLE EUROPEOS (€) | G55: TOTAL NO ELEGIBLE EUROPEOS (€) | H55: TOTAL MARGINAL (€) | I55: TOTAL AMORTIZACIÓN (€)
A56: VOLVER A EQUIPAMIENTO | B56: Suma del coste total del equipo 3 implicado en el desarrollo por UMC | D56: =SUM(D27,D31,D42,D53) -> 0 | F56: =SUMIF(F15:F52,"X",$D$15:$D$52) -> 0 | G56: =SUMIF(G15:G52,"X",$D$15:$D$52) -> 0 | H56: =SUMIF(H15:H52,"X",$D$15:$D$52) -> 0 | I56: =SUMIF(I15:I52,"X",$D$15:$D$52) -> 0

Sheet Equipo 4
A2: EQUIPO 4 (por UMC)
A4: UMC (€) | B4: =IF('Datos generales'!B11:C11="(Campo desplegable)","Indicar en la hoja de 'Datos generales'",'Datos generales'!B11:C11) -> Indicar en la hoja de 'Datos generales'
A6: =IF(Equipamiento!B13="Campo rellenable de descripción del equipo","Campo automático",Equipamiento!B13) -> Campo automático
A7: DATOS DE LA UTILIZACIÓN | B7: Información para el cálculo del coste
A8: Tipo de equipamiento | B8: (Campo desplegable)
A9: Indique si el equipo está amortizado | B9: (Campo desplegable)
A10: Periodo de amortización | B10: =IF(B8="(Campo desplegable)","Campo automático",VLOOKUP(B8,Referencias!A32:B33,2,FALSE)) -> Campo automático
A11: Tiempos de uso del equipo 4 | B11: Tiempo de utilización anual del equipo en horas | D11: 1
B12: Tiempo utilizado durante una UMC en hora/s y fracción | D12: 0
A13: UTILIZACIÓN DEL EQUIPO 4
A14: Energía | B14: Indique si la energía es: -Medida con un contador y valorada con las tarifas del contrato de suministro vigente -Estimada mediante facturas | D14: (Campo desplegable) | F14: ELEGIBLE EUROPEOS | G14: NO ELEGIBLE EUROPEOS | H14: MARGINAL | I14: AMORTIZACIÓN
B15: Coste de energía por UMC - IMPORTE SIN IVA (€) | D15: 0 | F15: =IF($D14="Medida con un contador","X","") | G15: =IF($D14="Estimada mediante facturas","X","") | H15: X
A16: Fungibles/Fluidos | B16: Incluir los costes - IMPORTE SIN IVA (€): Contables, número de fungibles o grupos de fungibles por coste unidad/grupo según facturas/mercado | D16: 0 | F16: X | H16: X
B17: Breve descripción de fungibles/fluidos utilizados ->
B18: Incluir los costes - IMPORTE SIN IVA (€): No contables (continuos), medida de consumo por coste UMC según facturas/mercado | D18: 0 | F18: X | H18: X
B19: Breve descripción de fungibles/fluidos utilizados ->
B20: Incluir los costes - IMPORTE SIN IVA (€): No contables (continuos), estimación de consumo por coste UMC según factura o precio de mercado | D20: 0 | G20: X | H20: X
B21: Breve descripción de fungibles/fluidos utilizados ->
A22: Amortización (si la antigüedad es inferior al periodo de amortización) | B22: Fecha de adquisición | D22: dd/mm/aaaa
B23: Valor de adquisición - IMPORTE SIN IVA (€) | D23: 0
B24: Subvención de la UE - IMPORTE SIN IVA (€) | D24: 0
B25: COSTES DE AMORTIZACIÓN ELEGIBLES PARA PROYECTOS DEL PROGRAMA MARCO POR UMC - IMPORTE SIN IVA (€) | D25: =IF(OR(B9="SÍ",B9="(Campo desplegable)"),0,((D23-D24)/B10)*(D12/D11)) -> 0 | F25: X | I25: X
B26: DIFERENCIA entre el coste de la amortización contable CSIC, C = (V/A)x t/T, donde V es el precio TOTAL de adquisición y A el periodo de amortización CSIC (véase tabla "Periodos amortización CSIC"), con el valor consignado en la casilla del coste elegible (el valor podría resultar negativo, como una corrección a la amortización acelerada que impone H2020). - IMPORTE SIN IVA (€) | D26: =IF(OR(B9="SÍ",B9="(Campo desplegable)"),0,((D23/B10)*(D12/D11))-D25) -> 0 | G26: X | I26: X
A27: COSTE TOTAL (UMC) UTILIZACIÓN DEL EQUIPO 4 | B27: → | D27: =SUM(D15,D16,D18,D20,D25,D26) -> 0 | F27: =SUMIF(F15:F26,"X",$D$15:$D$26) -> 0 | G27: =SUMIF(G15:G26,"X",$D$15:$D$26) -> 0 | H27: =SUMIF(H15:H26,"X",$D$15:$D$26) -> 0 | I27: =SUMIF(I15:I26,"X",$D$15:$D$26) -> 0
A29: MANTENIMIENTO EQUIPO 4
A30: Mantenimiento del equipo 4 (incluyendo calibraciones preprogramadas) | B30: Coste anual de reparación y mantenimiento (o media del coste de los últimos cinco años) - IMPORTE SIN IVA (€) | D30: 0
A31: COSTE TOTAL (UMC) MANTENIMIENTO EQUIPO 4 IMPORTE SIN IVA (€) | B31: → | D31: =(D30*D12/D11) -> 0 | G31: X
F32: =SUMIF(F30:F31,"X",$D$30:$D$31) -> 0 | G32: =SUMIF(G30:G31,"X",$D$30:$D$31) -> 0 | H32: =SUMIF(H30:H31,"X",$D$30:$D$31) -> 0 | I32: =SUMIF(I30:I31,"X",$D$30:$D$31) -> 0
A33: ARRANQUE/ENFRIAMIENTO EQUIPO 4
A34: Energía | B34: Energía por arranque/enfriamiento - IMPORTE SIN IVA (€) | D34: 0 | G34: X | H34: X
A35: Fungibles/Fluidos | B35: Fungibles/Fluidos por arranque/enfriamiento - IMPORTE SIN IVA (€) | D35: 0 | G35: X | H35: X
B36: Breve descripción de fungibles/fluidos utilizados ->
A37: Amortización | B37: Rellenar en caso de equipamiento en periodo de amortización
B38: Nº medio de UMC por arranque/enfriamiento | D38: 1
B39: Tiempo de arranque/enfriamiento en hora/s y fracción | D39: 0
B40: COSTES DE AMORTIZACIÓN NO ELEGIBLES PARA PROYECTOS DEL PROGRAMA MARCO - IMPORTE SIN IVA (€) | D40: =IF(OR(B9="SÍ",B9="(Campo desplegable)"),0,(D23/B10)*(D39/D11)) -> 0
B41: Amortización asociada al tiempo de arranque/enfriamiento por UMC - IMPORTE SIN IVA (€) | D41: =D40/D38 -> 0 | G41: X | I41: X
A42: COSTE TOTAL (UMC) ARRANQUE/ENFRIAMIENTO EQUIPO 4 IMPORTE SIN IVA (€) | B42: → | D42: =SUM(D34,D35,D41) -> 0 | F42: =SUMIF(F34:F41,"X",$D$34:$D$41) -> 0 | G42: =SUMIF(G34:G41,"X",$D$34:$D$41) -> 0 | H42: =SUMIF(H34:H41,"X",$D$34:$D$41) -> 0 | I42: =SUMIF(I34:I41,"X",$D$34:$D$41) -> 0
A44: CALIBRACIÓN INTERMEDIA DEL EQUIPO 4
A45: Energía | B45: Energía por calibración - IMPORTE SIN IVA (€) | D45: 0 | G45: X | H45: X
A46: Fungibles/Fluidos | B46: Fungibles/Fluidos por calibración - IMPORTE SIN IVA (€) | D46: 0 | G46: X | H46: X
B47: Breve descripción de fungibles/fluidos utilizados ->
A48: Amortización | B48: Rellenar en caso de equipamiento en periodo de amortización
B49: Nº medio de UMC por calibración | D49: 1
B50: Tiempo de la calibración en hora/s y fracción | D50: 0
B51: COSTES DE AMORTIZACIÓN NO ELEGIBLES PARA PROYECTOS DEL PROGRAMA MARCO - IMPORTE SIN IVA (€) | D51: =IF(OR(B9="SÍ",B9="(Campo desplegable)"),0,(D23/B10)*(D50/D11)) -> 0
B52: Amortización de la calibración por UMC - IMPORTE SIN IVA (€) | D52: =D51/D49 -> 0 | G52: X | I52: X
A53: COSTE TOTAL (UMC) CALIBRACIÓN INTERMEDIA DEL EQUIPO 4 (durante el transcurso de un grupo de prestaciones) IMPORTE SIN IVA (€) | B53: → | D53: =SUM(D45,D46,D52) -> 0 | F53: =SUMIF(F45:F52,"X",$D$45:$D$52) -> 0 | G53: =SUMIF(G45:G52,"X",$D$45:$D$52) -> 0 | H53: =SUMIF(H45:H52,"X",$D$45:$D$52) -> 0 | I53: =SUMIF(I45:I52,"X",$D$45:$D$52) -> 0
B55: COSTE TOTAL (UMC) EQUIPO 4 | D55: TOTAL IMPORTE SIN IVA (€) | F55: TOTAL ELEGIBLE EUROPEOS (€) | G55: TOTAL NO ELEGIBLE EUROPEOS (€) | H55: TOTAL MARGINAL (€) | I55: TOTAL AMORTIZACIÓN (€)
A56: VOLVER A EQUIPAMIENTO | B56: Suma del coste total del equipo 4 implicado en el desarrollo por UMC | D56: =SUM(D27,D31,D42,D53) -> 0 | F56: =SUMIF(F15:F52,"X",$D$15:$D$52) -> 0 | G56: =SUMIF(G15:G52,"X",$D$15:$D$52) -> 0 | H56: =SUMIF(H15:H52,"X",$D$15:$D$52) -> 0 | I56: =SUMIF(I15:I52,"X",$D$15:$D$52) -> 0

Sheet Equipo 5
A2: EQUIPO 5 (por UMC)
A4: UMC (€) | B4: =IF('Datos generales'!B11:C11="(Campo desplegable)","Indicar en la hoja de 'Datos generales'",'Datos generales'!B11:C11) -> Indicar en la hoja de 'Datos generales'
A6: =IF(Equipamiento!B14="Campo rellenable de descripción del equipo","Campo automático",Equipamiento!B14) -> Campo automático
A7: DATOS DE LA UTILIZACIÓN | B7: Información para el cálculo del coste
A8: Tipo de equipamiento | B8: (Campo desplegable)
A9: Indique si el equipo está amortizado | B9: (Campo desplegable)
A10: Periodo de amortización | B10: =IF(B8="(Campo desplegable)","Campo automático",VLOOKUP(B8,Referencias!A32:B33,2,FALSE)) -> Campo automático
A11: Tiempos de uso del equipo 5 | B11: Tiempo de utilización anual del equipo en horas | D11: 1
B12: Tiempo utilizado durante una UMC en hora/s y fracción | D12: 0
A13: UTILIZACIÓN DEL EQUIPO 5
A14: Energía | B14: Indique si la energía es: -Medida con un contador y valorada con las tarifas del contrato de suministro vigente -Estimada mediante facturas | D14: (Campo desplegable) | F14: ELEGIBLE EUROPEOS | G14: NO ELEGIBLE EUROPEOS | H14: MARGINAL | I14: AMORTIZACIÓN
B15: Coste de energía por UMC - IMPORTE SIN IVA (€) | D15: 0 | F15: =IF($D14="Medida con un contador","X","") | G15: =IF($D14="Estimada mediante facturas","X","") | H15: X
A16: Fungibles/Fluidos | B16: Incluir los costes - IMPORTE SIN IVA (€): Contables, número de fungibles o grupos de fungibles por coste unidad/grupo según facturas/mercado | D16: 0 | F16: X | H16: X
B17: Breve descripción de fungibles/fluidos utilizados ->
B18: Incluir los costes - IMPORTE SIN IVA (€): No contables (continuos), medida de consumo por coste UMC según facturas/mercado | D18: 0 | F18: X | H18: X
B19: Breve descripción de fungibles/fluidos utilizados ->
B20: Incluir los costes - IMPORTE SIN IVA (€): No contables (continuos), estimación de consumo por coste UMC según factura o precio de mercado | D20: 0 | G20: X | H20: X
B21: Breve descripción de fungibles/fluidos utilizados ->
A22: Amortización (si la antigüedad es inferior al periodo de amortización) | B22: Fecha de adquisición | D22: dd/mm/aaaa
B23: Valor de adquisición - IMPORTE SIN IVA (€) | D23: 0
B24: Subvención de la UE - IMPORTE SIN IVA (€) | D24: 0
B25: COSTES DE AMORTIZACIÓN ELEGIBLES PARA PROYECTOS DEL PROGRAMA MARCO POR UMC - IMPORTE SIN IVA (€) | D25: =IF(OR(B9="SÍ",B9="(Campo desplegable)"),0,((D23-D24)/B10)*(D12/D11)) -> 0 | F25: X | I25: X
B26: DIFERENCIA entre el coste de la amortización contable CSIC, C = (V/A)x t/T, donde V es el precio TOTAL de adquisición y A el periodo de amortización CSIC (véase tabla "Periodos amortización CSIC"), con el valor consignado en la casilla del coste elegible (el valor podría resultar negativo, como una corrección a la amortización acelerada que impone H2020). - IMPORTE SIN IVA (€) | D26: =IF(OR(B9="SÍ",B9="(Campo desplegable)"),0,((D23/B10)*(D12/D11))-D25) -> 0 | G26: X | I26: X
A27: COSTE TOTAL (UMC) UTILIZACIÓN DEL EQUIPO 5 | B27: → | D27: =SUM(D15,D16,D18,D20,D25,D26) -> 0 | F27: =SUMIF(F15:F26,"X",$D$15:$D$26) -> 0 | G27: =SUMIF(G15:G26,"X",$D$15:$D$26) -> 0 | H27: =SUMIF(H15:H26,"X",$D$15:$D$26) -> 0 | I27: =SUMIF(I15:I26,"X",$D$15:$D$26) -> 0
A29: MANTENIMIENTO EQUIPO 5
A30: Mantenimiento del equipo 5 (incluyendo calibraciones preprogramadas) | B30: Coste anual de reparación y mantenimiento (o media del coste de los últimos cinco años) - IMPORTE SIN IVA (€) | D30: 0
A31: COSTE TOTAL (UMC) MANTENIMIENTO EQUIPO 5 IMPORTE SIN IVA (€) | B31: → | D31: =(D30*D12/D11) -> 0 | G31: X
F32: =SUMIF(F30:F31,"X",$D$30:$D$31) -> 0 | G32: =SUMIF(G30:G31,"X",$D$30:$D$31) -> 0 | H32: =SUMIF(H30:H31,"X",$D$30:$D$31) -> 0 | I32: =SUMIF(I30:I31,"X",$D$30:$D$31) -> 0
A33: ARRANQUE/ENFRIAMIENTO EQUIPO 5
A34: Energía | B34: Energía por arranque/enfriamiento - IMPORTE SIN IVA (€) | D34: 0 | G34: X | H34: X
A35: Fungibles/Fluidos | B35: Fungibles/Fluidos por arranque/enfriamiento - IMPORTE SIN IVA (€) | D35: 0 | G35: X | H35: X
B36: Breve descripción de fungibles/fluidos utilizados ->
A37: Amortización | B37: Rellenar en caso de equipamiento en periodo de amortización
B38: Nº medio de UMC por arranque/enfriamiento | D38: 1
B39: Tiempo de arranque/enfriamiento en hora/s y fracción | D39: 0
B40: COSTES DE AMORTIZACIÓN NO ELEGIBLES PARA PROYECTOS DEL PROGRAMA MARCO - IMPORTE SIN IVA (€) | D40: =IF(OR(B9="SÍ",B9="(Campo desplegable)"),0,(D23/B10)*(D39/D11)) -> 0
B41: Amortización asociada al tiempo de arranque/enfriamiento por UMC - IMPORTE SIN IVA (€) | D41: =D40/D38 -> 0 | G41: X | I41: X
A42: COSTE TOTAL (UMC) ARRANQUE/ENFRIAMIENTO EQUIPO 5 IMPORTE SIN IVA (€) | B42: → | D42: =SUM(D34,D35,D41) -> 0 | F42: =SUMIF(F34:F41,"X",$D$34:$D$41) -> 0 | G42: =SUMIF(G34:G41,"X",$D$34:$D$41) -> 0 | H42: =SUMIF(H34:H41,"X",$D$34:$D$41) -> 0 | I42: =SUMIF(I34:I41,"X",$D$34:$D$41) -> 0
A44: CALIBRACIÓN INTERMEDIA DEL EQUIPO 5
A45: Energía | B45: Energía por calibración - IMPORTE SIN IVA (€) | D45: 0 | G45: X | H45: X
A46: Fungibles/Fluidos | B46: Fungibles/Fluidos por calibración - IMPORTE SIN IVA (€) | D46: 0 | G46: X | H46: X
B47: Breve descripción de fungibles/fluidos utilizados ->
A48: Amortización | B48: Rellenar en caso de equipamiento en periodo de amortización
B49: Nº medio de UMC por calibración | D49: 1
B50: Tiempo de la calibración en hora/s y fracción | D50: 0
B51: COSTES DE AMORTIZACIÓN NO ELEGIBLES PARA PROYECTOS DEL PROGRAMA MARCO - IMPORTE SIN IVA (€) | D51: =IF(OR(B9="SÍ",B9="(Campo desplegable)"),0,(D23/B10)*(D50/D11)) -> 0
B52: Amortización de la calibración por UMC - IMPORTE SIN IVA (€) | D52: =D51/D49 -> 0 | G52: X | I52: X
A53: COSTE TOTAL (UMC) CALIBRACIÓN INTERMEDIA DEL EQUIPO 5 (durante el transcurso de un grupo de prestaciones) IMPORTE SIN IVA (€) | B53: → | D53: =SUM(D45,D46,D52) -> 0 | F53: =SUMIF(F45:F52,"X",$D$45:$D$52) -> 0 | G53: =SUMIF(G45:G52,"X",$D$45:$D$52) -> 0 | H53: =SUMIF(H45:H52,"X",$D$45:$D$52) -> 0 | I53: =SUMIF(I45:I52,"X",$D$45:$D$52) -> 0
B55: COSTE TOTAL (UMC) EQUIPO 5 | D55: TOTAL IMPORTE SIN IVA (€) | F55: TOTAL ELEGIBLE EUROPEOS (€) | G55: TOTAL NO ELEGIBLE EUROPEOS (€) | H55: TOTAL MARGINAL (€) | I55: TOTAL AMORTIZACIÓN (€)
A56: VOLVER A EQUIPAMIENTO | B56: Suma del coste total del equipo 5 implicado en el desarrollo por UMC | D56: =SUM(D27,D31,D42,D53) -> 0 | F56: =SUMIF(F15:F52,"X",$D$15:$D$52) -> 0 | G56: =SUMIF(G15:G52,"X",$D$15:$D$52) -> 0 | H56: =SUMIF(H15:H52,"X",$D$15:$D$52) -> 0 | I56: =SUMIF(I15:I52,"X",$D$15:$D$52) -> 0

Sheet Equipo 6
A2: EQUIPO 6 (por UMC)
A4: UMC (€) | B4: =IF('Datos generales'!B11:C11="(Campo desplegable)","Indicar en la hoja de 'Datos generales'",'Datos generales'!B11:C11) -> Indicar en la hoja de 'Datos generales'
A6: =IF(Equipamiento!B15="Campo rellenable de descripción del equipo","Campo automático",Equipamiento!B15) -> Campo automático
A7: DATOS DE LA UTILIZACIÓN | B7: Información para el cálculo del coste
A8: Tipo de equipamiento | B8: (Campo desplegable)
A9: Indique si el equipo está amortizado | B9: (Campo desplegable)
A10: Periodo de amortización | B10: =IF(B8="(Campo desplegable)","Campo automático",VLOOKUP(B8,Referencias!A32:B33,2,FALSE)) -> Campo automático
A11: Tiempos de uso del equipo 6 | B11: Tiempo de utilización anual del equipo en horas | D11: 1
B12: Tiempo utilizado durante una UMC en hora/s y fracción | D12: 0
A13: UTILIZACIÓN DEL EQUIPO 6
A14: Energía | B14: Indique si la energía es: -Medida con un contador y valorada con las tarifas del contrato de suministro vigente -Estimada mediante facturas | D14: (Campo desplegable) | F14: ELEGIBLE EUROPEOS | G14: NO ELEGIBLE EUROPEOS | H14: MARGINAL | I14: AMORTIZACIÓN
B15: Coste de energía por UMC - IMPORTE SIN IVA (€) | D15: 0 | F15: =IF($D14="Medida con un contador","X","") | G15: =IF($D14="Estimada mediante facturas","X","") | H15: X
A16: Fungibles/Fluidos | B16: Incluir los costes - IMPORTE SIN IVA (€): Contables, número de fungibles o grupos de fungibles por coste unidad/grupo según facturas/mercado | D16: 0 | F16: X | H16: X
B17: Breve descripción de fungibles/fluidos utilizados ->
B18: Incluir los costes - IMPORTE SIN IVA (€): No contables (continuos), medida de consumo por coste UMC según facturas/mercado | D18: 0 | F18: X | H18: X
B19: Breve descripción de fungibles/fluidos utilizados ->
B20: Incluir los costes - IMPORTE SIN IVA (€): No contables (continuos), estimación de consumo por coste UMC según factura o precio de mercado | D20: 0 | G20: X | H20: X
B21: Breve descripción de fungibles/fluidos utilizados ->
A22: Amortización (si la antigüedad es inferior al periodo de amortización) | B22: Fecha de adquisición | D22: dd/mm/aaaa
B23: Valor de adquisición - IMPORTE SIN IVA (€) | D23: 0
B24: Subvención de la UE - IMPORTE SIN IVA (€) | D24: 0
B25: COSTES DE AMORTIZACIÓN ELEGIBLES PARA PROYECTOS DEL PROGRAMA MARCO POR UMC - IMPORTE SIN IVA (€) | D25: =IF(OR(B9="SÍ",B9="(Campo desplegable)"),0,((D23-D24)/B10)*(D12/D11)) -> 0 | F25: X | I25: X
B26: DIFERENCIA entre el coste de la amortización contable CSIC, C = (V/A)x t/T, donde V es el precio TOTAL de adquisición y A el periodo de amortización CSIC (véase tabla "Periodos amortización CSIC"), con el valor consignado en la casilla del coste elegible (el valor podría resultar negativo, como una corrección a la amortización acelerada que impone H2020). - IMPORTE SIN IVA (€) | D26: =IF(OR(B9="SÍ",B9="(Campo desplegable)"),0,((D23/B10)*(D12/D11))-D25) -> 0 | G26: X | I26: X
A27: COSTE TOTAL (UMC) UTILIZACIÓN DEL EQUIPO 6 | B27: → | D27: =SUM(D15,D16,D18,D20,D25,D26) -> 0 | F27: =SUMIF(F15:F26,"X",$D$15:$D$26) -> 0 | G27: =SUMIF(G15:G26,"X",$D$15:$D$26) -> 0 | H27: =SUMIF(H15:H26,"X",$D$15:$D$26) -> 0 | I27: =SUMIF(I15:I26,"X",$D$15:$D$26) -> 0
A29: MANTENIMIENTO EQUIPO 6
A30: Mantenimiento del equipo 6 (incluyendo calibraciones preprogramadas) | B30: Coste anual de reparación y mantenimiento (o media del coste de los últimos cinco años) - IMPORTE SIN IVA (€) | D30: 0
A31: COSTE TOTAL (UMC) MANTENIMIENTO EQUIPO 6 IMPORTE SIN IVA (€) | B31: → | D31: =(D30*D12/D11) -> 0 | G31: X
F32: =SUMIF(F30:F31,"X",$D$30:$D$31) -> 0 | G32: =SUMIF(G30:G31,"X",$D$30:$D$31) -> 0 | H32: =SUMIF(H30:H31,"X",$D$30:$D$31) -> 0 | I32: =SUMIF(I30:I31,"X",$D$30:$D$31) -> 0
A33: ARRANQUE/ENFRIAMIENTO EQUIPO 6
A34: Energía | B34: Energía por arranque/enfriamiento - IMPORTE SIN IVA (€) | D34: 0 | G34: X | H34: X
A35: Fungibles/Fluidos | B35: Fungibles/Fluidos por arranque/enfriamiento - IMPORTE SIN IVA (€) | D35: 0 | G35: X | H35: X
B36: Breve descripción de fungibles/fluidos utilizados ->
A37: Amortización | B37: Rellenar en caso de equipamiento en periodo de amortización
B38: Nº medio de UMC por arranque/enfriamiento | D38: 1
B39: Tiempo de arranque/enfriamiento en hora/s y fracción | D39: 0
B40: COSTES DE AMORTIZACIÓN NO ELEGIBLES PARA PROYECTOS DEL PROGRAMA MARCO - IMPORTE SIN IVA (€) | D40: =IF(OR(B9="SÍ",B9="(Campo desplegable)"),0,(D23/B10)*(D39/D11)) -> 0
B41: Amortización asociada al tiempo de arranque/enfriamiento por UMC - IMPORTE SIN IVA (€) | D41: =D40/D38 -> 0 | G41: X | I41: X
A42: COSTE TOTAL (UMC) ARRANQUE/ENFRIAMIENTO EQUIPO 6 IMPORTE SIN IVA (€) | B42: → | D42: =SUM(D34,D35,D41) -> 0 | F42: =SUMIF(F34:F41,"X",$D$34:$D$41) -> 0 | G42: =SUMIF(G34:G41,"X",$D$34:$D$41) -> 0 | H42: =SUMIF(H34:H41,"X",$D$34:$D$41) -> 0 | I42: =SUMIF(I34:I41,"X",$D$34:$D$41) -> 0
A44: CALIBRACIÓN INTERMEDIA DEL EQUIPO 6
A45: Energía | B45: Energía por calibración - IMPORTE SIN IVA (€) | D45: 0 | G45: X | H45: X
A46: Fungibles/Fluidos | B46: Fungibles/Fluidos por calibración - IMPORTE SIN IVA (€) | D46: 0 | G46: X | H46: X
B47: Breve descripción de fungibles/fluidos utilizados ->
A48: Amortización | B48: Rellenar en caso de equipamiento en periodo de amortización
B49: Nº medio de UMC por calibración | D49: 1
B50: Tiempo de la calibración en hora/s y fracción | D50: 0
B51: COSTES DE AMORTIZACIÓN NO ELEGIBLES PARA PROYECTOS DEL PROGRAMA MARCO - IMPORTE SIN IVA (€) | D51: =IF(OR(B9="SÍ",B9="(Campo desplegable)"),0,(D23/B10)*(D50/D11)) -> 0
B52: Amortización de la calibración por UMC - IMPORTE SIN IVA (€) | D52: =D51/D49 -> 0 | G52: X | I52: X
A53: COSTE TOTAL (UMC) CALIBRACIÓN INTERMEDIA DEL EQUIPO 6 (durante el transcurso de un grupo de prestaciones) IMPORTE SIN IVA (€) | B53: → | D53: =SUM(D45,D46,D52) -> 0 | F53: =SUMIF(F45:F52,"X",$D$45:$D$52) -> 0 | G53: =SUMIF(G45:G52,"X",$D$45:$D$52) -> 0 | H53: =SUMIF(H45:H52,"X",$D$45:$D$52) -> 0 | I53: =SUMIF(I45:I52,"X",$D$45:$D$52) -> 0
B55: COSTE TOTAL (UMC) EQUIPO 6 | D55: TOTAL IMPORTE SIN IVA (€) | F55: TOTAL ELEGIBLE EUROPEOS (€) | G55: TOTAL NO ELEGIBLE EUROPEOS (€) | H55: TOTAL MARGINAL (€) | I55: TOTAL AMORTIZACIÓN (€)
A56: VOLVER A EQUIPAMIENTO | B56: Suma del coste total del equipo 6 implicado en el desarrollo por UMC | D56: =SUM(D27,D31,D42,D53) -> 0 | F56: =SUMIF(F15:F52,"X",$D$15:$D$52) -> 0 | G56: =SUMIF(G15:G52,"X",$D$15:$D$52) -> 0 | H56: =SUMIF(H15:H52,"X",$D$15:$D$52) -> 0 | I56: =SUMIF(I15:I52,"X",$D$15:$D$52) -> 0

Sheet Equipo 7
A2: EQUIPO 7 (por UMC)
A4: UMC (€) | B4: =IF('Datos generales'!B11:C11="(Campo desplegable)","Indicar en la hoja de 'Datos generales'",'Datos generales'!B11:C11) -> Indicar en la hoja de 'Datos generales'
A6: =IF(Equipamiento!B16="Campo rellenable de descripción del equipo","Campo automático",Equipamiento!B16) -> Campo automático
A7: DATOS DE LA UTILIZACIÓN | B7: Información para el cálculo del coste
A8: Tipo de equipamiento | B8: (Campo desplegable)
A9: Indique si el equipo está amortizado | B9: (Campo desplegable)
A10: Periodo de amortización | B10: =IF(B8="(Campo desplegable)","Campo automático",VLOOKUP(B8,Referencias!A32:B33,2,FALSE)) -> Campo automático
A11: Tiempos de uso del equipo 7 | B11: Tiempo de utilización anual del equipo en horas | D11: 1
B12: Tiempo utilizado durante una UMC en hora/s y fracción | D12: 0
A13: UTILIZACIÓN DEL EQUIPO 7
A14: Energía | B14: Indique si la energía es: -Medida con un contador y valorada con las tarifas del contrato de suministro vigente -Estimada mediante facturas | D14: (Campo desplegable) | F14: ELEGIBLE EUROPEOS | G14: NO ELEGIBLE EUROPEOS | H14: MARGINAL | I14: AMORTIZACIÓN
B15: Coste de energía por UMC - IMPORTE SIN IVA (€) | D15: 0 | F15: =IF($D14="Medida con un contador","X","") | G15: =IF($D14="Estimada mediante facturas","X","") | H15: X
A16: Fungibles/Fluidos | B16: Incluir los costes - IMPORTE SIN IVA (€): Contables, número de fungibles o grupos de fungibles por coste unidad/grupo según facturas/mercado | D16: 0 | F16: X | H16: X
B17: Breve descripción de fungibles/fluidos utilizados ->
B18: Incluir los costes - IMPORTE SIN IVA (€): No contables (continuos), medida de consumo por coste UMC según facturas/mercado | D18: 0 | F18: X | H18: X
B19: Breve descripción de fungibles/fluidos utilizados ->
B20: Incluir los costes - IMPORTE SIN IVA (€): No contables (continuos), estimación de consumo por coste UMC según factura o precio de mercado | D20: 0 | G20: X | H20: X
B21: Breve descripción de fungibles/fluidos utilizados ->
A22: Amortización (si la antigüedad es inferior al periodo de amortización) | B22: Fecha de adquisición | D22: dd/mm/aaaa
B23: Valor de adquisición - IMPORTE SIN IVA (€) | D23: 0
B24: Subvención de la UE - IMPORTE SIN IVA (€) | D24: 0
B25: COSTES DE AMORTIZACIÓN ELEGIBLES PARA PROYECTOS DEL PROGRAMA MARCO POR UMC - IMPORTE SIN IVA (€) | D25: =IF(OR(B9="SÍ",B9="(Campo desplegable)"),0,((D23-D24)/B10)*(D12/D11)) -> 0 | F25: X | I25: X
B26: DIFERENCIA entre el coste de la amortización contable CSIC, C = (V/A)x t/T, donde V es el precio TOTAL de adquisición y A el periodo de amortización CSIC (véase tabla "Periodos amortización CSIC"), con el valor consignado en la casilla del coste elegible (el valor podría resultar negativo, como una corrección a la amortización acelerada que impone H2020). - IMPORTE SIN IVA (€) | D26: =IF(OR(B9="SÍ",B9="(Campo desplegable)"),0,((D23/B10)*(D12/D11))-D25) -> 0 | G26: X | I26: X
A27: COSTE TOTAL (UMC) UTILIZACIÓN DEL EQUIPO 7 | B27: → | D27: =SUM(D15,D16,D18,D20,D25,D26) -> 0 | F27: =SUMIF(F15:F26,"X",$D$15:$D$26) -> 0 | G27: =SUMIF(G15:G26,"X",$D$15:$D$26) -> 0 | H27: =SUMIF(H15:H26,"X",$D$15:$D$26) -> 0 | I27: =SUMIF(I15:I26,"X",$D$15:$D$26) -> 0
A29: MANTENIMIENTO EQUIPO 7
A30: Mantenimiento del equipo 7 (incluyendo calibraciones preprogramadas) | B30: Coste anual de reparación y mantenimiento (o media del coste de los últimos cinco años) - IMPORTE SIN IVA (€) | D30: 0
A31: COSTE TOTAL (UMC) MANTENIMIENTO EQUIPO 7 IMPORTE SIN IVA (€) | B31: → | D31: =(D30*D12/D11) -> 0 | G31: X
F32: =SUMIF(F30:F31,"X",$D$30:$D$31) -> 0 | G32: =SUMIF(G30:G31,"X",$D$30:$D$31) -> 0 | H32: =SUMIF(H30:H31,"X",$D$30:$D$31) -> 0 | I32: =SUMIF(I30:I31,"X",$D$30:$D$31) -> 0
A33: ARRANQUE/ENFRIAMIENTO EQUIPO 7
A34: Energía | B34: Energía por arranque/enfriamiento - IMPORTE SIN IVA (€) | D34: 0 | G34: X | H34: X
A35: Fungibles/Fluidos | B35: Fungibles/Fluidos por arranque/enfriamiento - IMPORTE SIN IVA (€) | D35: 0 | G35: X | H35: X
B36: Breve descripción de fungibles/fluidos utilizados ->
A37: Amortización | B37: Rellenar en caso de equipamiento en periodo de amortización
B38: Nº medio de UMC por arranque/enfriamiento | D38: 1
B39: Tiempo de arranque/enfriamiento en hora/s y fracción | D39: 0
B40: COSTES DE AMORTIZACIÓN NO ELEGIBLES PARA PROYECTOS DEL PROGRAMA MARCO - IMPORTE SIN IVA (€) | D40: =IF(OR(B9="SÍ",B9="(Campo desplegable)"),0,(D23/B10)*(D39/D11)) -> 0
B41: Amortización asociada al tiempo de arranque/enfriamiento por UMC - IMPORTE SIN IVA (€) | D41: =D40/D38 -> 0 | G41: X | I41: X
A42: COSTE TOTAL (UMC) ARRANQUE/ENFRIAMIENTO EQUIPO 7 IMPORTE SIN IVA (€) | B42: → | D42: =SUM(D34,D35,D41) -> 0 | F42: =SUMIF(F34:F41,"X",$D$34:$D$41) -> 0 | G42: =SUMIF(G34:G41,"X",$D$34:$D$41) -> 0 | H42: =SUMIF(H34:H41,"X",$D$34:$D$41) -> 0 | I42: =SUMIF(I34:I41,"X",$D$34:$D$41) -> 0
A44: CALIBRACIÓN INTERMEDIA DEL EQUIPO 7
A45: Energía | B45: Energía por calibración - IMPORTE SIN IVA (€) | D45: 0 | G45: X | H45: X
A46: Fungibles/Fluidos | B46: Fungibles/Fluidos por calibración - IMPORTE SIN IVA (€) | D46: 0 | G46: X | H46: X
B47: Breve descripción de fungibles/fluidos utilizados ->
A48: Amortización | B48: Rellenar en caso de equipamiento en periodo de amortización
B49: Nº medio de UMC por calibración | D49: 1
B50: Tiempo de la calibración en hora/s y fracción | D50: 0
B51: COSTES DE AMORTIZACIÓN NO ELEGIBLES PARA PROYECTOS DEL PROGRAMA MARCO - IMPORTE SIN IVA (€) | D51: =IF(OR(B9="SÍ",B9="(Campo desplegable)"),0,(D23/B10)*(D50/D11)) -> 0
B52: Amortización de la calibración por UMC - IMPORTE SIN IVA (€) | D52: =D51/D49 -> 0 | G52: X | I52: X
A53: COSTE TOTAL (UMC) CALIBRACIÓN INTERMEDIA DEL EQUIPO 7 (durante el transcurso de un grupo de prestaciones) IMPORTE SIN IVA (€) | B53: → | D53: =SUM(D45,D46,D52) -> 0 | F53: =SUMIF(F45:F52,"X",$D$45:$D$52) -> 0 | G53: =SUMIF(G45:G52,"X",$D$45:$D$52) -> 0 | H53: =SUMIF(H45:H52,"X",$D$45:$D$52) -> 0 | I53: =SUMIF(I45:I52,"X",$D$45:$D$52) -> 0
B55: COSTE TOTAL (UMC) EQUIPO 7 | D55: TOTAL IMPORTE SIN IVA (€) | F55: TOTAL ELEGIBLE EUROPEOS (€) | G55: TOTAL NO ELEGIBLE EUROPEOS (€) | H55: TOTAL MARGINAL (€) | I55: TOTAL AMORTIZACIÓN (€)
A56: VOLVER A EQUIPAMIENTO | B56: Suma del coste total del equipo 7 implicado en el desarrollo por UMC | D56: =SUM(D27,D31,D42,D53) -> 0 | F56: =SUMIF(F15:F52,"X",$D$15:$D$52) -> 0 | G56: =SUMIF(G15:G52,"X",$D$15:$D$52) -> 0 | H56: =SUMIF(H15:H52,"X",$D$15:$D$52) -> 0 | I56: =SUMIF(I15:I52,"X",$D$15:$D$52) -> 0

Sheet Equipo 8
A2: EQUIPO 8 (por UMC)
A4: UMC (€) | B4: =IF('Datos generales'!B11:C11="(Campo desplegable)","Indicar en la hoja de 'Datos generales'",'Datos generales'!B11:C11) -> Indicar en la hoja de 'Datos generales'
A6: =IF(Equipamiento!B17="Campo rellenable de descripción del equipo","Campo automático",Equipamiento!B17) -> Campo automático
A7: DATOS DE LA UTILIZACIÓN | B7: Información para el cálculo del coste
A8: Tipo de equipamiento | B8: (Campo desplegable)
A9: Indique si el equipo está amortizado | B9: (Campo desplegable)
A10: Periodo de amortización | B10: =IF(B8="(Campo desplegable)","Campo automático",VLOOKUP(B8,Referencias!A32:B33,2,FALSE)) -> Campo automático
A11: Tiempos de uso del equipo 8 | B11: Tiempo de utilización anual del equipo en horas | D11: 1
B12: Tiempo utilizado durante una UMC en hora/s y fracción | D12: 0
A13: UTILIZACIÓN DEL EQUIPO 8
A14: Energía | B14: Indique si la energía es: -Medida con un contador y valorada con las tarifas del contrato de suministro vigente -Estimada mediante facturas | D14: (Campo desplegable) | F14: ELEGIBLE EUROPEOS | G14: NO ELEGIBLE EUROPEOS | H14: MARGINAL | I14: AMORTIZACIÓN
B15: Coste de energía por UMC - IMPORTE SIN IVA (€) | D15: 0 | F15: =IF($D14="Medida con un contador","X","") | G15: =IF($D14="Estimada mediante facturas","X","") | H15: X
A16: Fungibles/Fluidos | B16: Incluir los costes - IMPORTE SIN IVA (€): Contables, número de fungibles o grupos de fungibles por coste unidad/grupo según facturas/mercado | D16: 0 | F16: X | H16: X
B17: Breve descripción de fungibles/fluidos utilizados ->
B18: Incluir los costes - IMPORTE SIN IVA (€): No contables (continuos), medida de consumo por coste UMC según facturas/mercado | D18: 0 | F18: X | H18: X
B19: Breve descripción de fungibles/fluidos utilizados ->
B20: Incluir los costes - IMPORTE SIN IVA (€): No contables (continuos), estimación de consumo por coste UMC según factura o precio de mercado | D20: 0 | G20: X | H20: X
B21: Breve descripción de fungibles/fluidos utilizados ->
A22: Amortización (si la antigüedad es inferior al periodo de amortización) | B22: Fecha de adquisición | D22: dd/mm/aaaa
B23: Valor de adquisición - IMPORTE SIN IVA (€) | D23: 0
B24: Subvención de la UE - IMPORTE SIN IVA (€) | D24: 0
B25: COSTES DE AMORTIZACIÓN ELEGIBLES PARA PROYECTOS DEL PROGRAMA MARCO POR UMC - IMPORTE SIN IVA (€) | D25: =IF(OR(B9="SÍ",B9="(Campo desplegable)"),0,((D23-D24)/B10)*(D12/D11)) -> 0 | F25: X | I25: X
B26: DIFERENCIA entre el coste de la amortización contable CSIC, C = (V/A)x t/T, donde V es el precio TOTAL de adquisición y A el periodo de amortización CSIC (véase tabla "Periodos amortización CSIC"), con el valor consignado en la casilla del coste elegible (el valor podría resultar negativo, como una corrección a la amortización acelerada que impone H2020). - IMPORTE SIN IVA (€) | D26: =IF(OR(B9="SÍ",B9="(Campo desplegable)"),0,((D23/B10)*(D12/D11))-D25) -> 0 | G26: X | I26: X
A27: COSTE TOTAL (UMC) UTILIZACIÓN DEL EQUIPO 8 | B27: → | D27: =SUM(D15,D16,D18,D20,D25,D26) -> 0 | F27: =SUMIF(F15:F26,"X",$D$15:$D$26) -> 0 | G27: =SUMIF(G15:G26,"X",$D$15:$D$26) -> 0 | H27: =SUMIF(H15:H26,"X",$D$15:$D$26) -> 0 | I27: =SUMIF(I15:I26,"X",$D$15:$D$26) -> 0
A29: MANTENIMIENTO EQUIPO 8
A30: Mantenimiento del equipo 8 (incluyendo calibraciones preprogramadas) | B30: Coste anual de reparación y mantenimiento (o media del coste de los últimos cinco años) - IMPORTE SIN IVA (€) | D30: 0
A31: COSTE TOTAL (UMC) MANTENIMIENTO EQUIPO 8 IMPORTE SIN IVA (€) | B31: → | D31: =(D30*D12/D11) -> 0 | G31: X
F32: =SUMIF(F30:F31,"X",$D$30:$D$31) -> 0 | G32: =SUMIF(G30:G31,"X",$D$30:$D$31) -> 0 | H32: =SUMIF(H30:H31,"X",$D$30:$D$31) -> 0 | I32: =SUMIF(I30:I31,"X",$D$30:$D$31) -> 0
A33: ARRANQUE/ENFRIAMIENTO EQUIPO 8
A34: Energía | B34: Energía por arranque/enfriamiento - IMPORTE SIN IVA (€) | D34: 0 | G34: X | H34: X
A35: Fungibles/Fluidos | B35: Fungibles/Fluidos por arranque/enfriamiento - IMPORTE SIN IVA (€) | D35: 0 | G35: X | H35: X
B36: Breve descripción de fungibles/fluidos utilizados ->
A37: Amortización | B37: Rellenar en caso de equipamiento en periodo de amortización
B38: Nº medio de UMC por arranque/enfriamiento | D38: 1
B39: Tiempo de arranque/enfriamiento en hora/s y fracción | D39: 0
B40: COSTES DE AMORTIZACIÓN NO ELEGIBLES PARA PROYECTOS DEL PROGRAMA MARCO - IMPORTE SIN IVA (€) | D40: =IF(OR(B9="SÍ",B9="(Campo desplegable)"),0,(D23/B10)*(D39/D11)) -> 0
B41: Amortización asociada al tiempo de arranque/enfriamiento por UMC - IMPORTE SIN IVA (€) | D41: =D40/D38 -> 0 | G41: X | I41: X
A42: COSTE TOTAL (UMC) ARRANQUE/ENFRIAMIENTO EQUIPO 8 IMPORTE SIN IVA (€) | B42: → | D42: =SUM(D34,D35,D41) -> 0 | F42: =SUMIF(F34:F41,"X",$D$34:$D$41) -> 0 | G42: =SUMIF(G34:G41,"X",$D$34:$D$41) -> 0 | H42: =SUMIF(H34:H41,"X",$D$34:$D$41) -> 0 | I42: =SUMIF(I34:I41,"X",$D$34:$D$41) -> 0
A44: CALIBRACIÓN INTERMEDIA DEL EQUIPO 8
A45: Energía | B45: Energía por calibración - IMPORTE SIN IVA (€) | D45: 0 | G45: X | H45: X
A46: Fungibles/Fluidos | B46: Fungibles/Fluidos por calibración - IMPORTE SIN IVA (€) | D46: 0 | G46: X | H46: X
B47: Breve descripción de fungibles/fluidos utilizados ->
A48: Amortización | B48: Rellenar en caso de equipamiento en periodo de amortización
B49: Nº medio de UMC por calibración | D49: 1
B50: Tiempo de la calibración en hora/s y fracción | D50: 0
B51: COSTES DE AMORTIZACIÓN NO ELEGIBLES PARA PROYECTOS DEL PROGRAMA MARCO - IMPORTE SIN IVA (€) | D51: =IF(OR(B9="SÍ",B9="(Campo desplegable)"),0,(D23/B10)*(D50/D11)) -> 0
B52: Amortización de la calibración por UMC - IMPORTE SIN IVA (€) | D52: =D51/D49 -> 0 | G52: X | I52: X
A53: COSTE TOTAL (UMC) CALIBRACIÓN INTERMEDIA DEL EQUIPO 8 (durante el transcurso de un grupo de prestaciones) IMPORTE SIN IVA (€) | B53: → | D53: =SUM(D45,D46,D52) -> 0 | F53: =SUMIF(F45:F52,"X",$D$45:$D$52) -> 0 | G53: =SUMIF(G45:G52,"X",$D$45:$D$52) -> 0 | H53: =SUMIF(H45:H52,"X",$D$45:$D$52) -> 0 | I53: =SUMIF(I45:I52,"X",$D$45:$D$52) -> 0
B55: COSTE TOTAL (UMC) EQUIPO 8 | D55: TOTAL IMPORTE SIN IVA (€) | F55: TOTAL ELEGIBLE EUROPEOS (€) | G55: TOTAL NO ELEGIBLE EUROPEOS (€) | H55: TOTAL MARGINAL (€) | I55: TOTAL AMORTIZACIÓN (€)
A56: VOLVER A EQUIPAMIENTO | B56: Suma del coste total del equipo 8 implicado en el desarrollo por UMC | D56: =SUM(D27,D31,D42,D53) -> 0 | F56: =SUMIF(F15:F52,"X",$D$15:$D$52) -> 0 | G56: =SUMIF(G15:G52,"X",$D$15:$D$52) -> 0 | H56: =SUMIF(H15:H52,"X",$D$15:$D$52) -> 0 | I56: =SUMIF(I15:I52,"X",$D$15:$D$52) -> 0

Sheet Equipo 9
A2: EQUIPO 9 (por UMC)
A4: UMC (€) | B4: =IF('Datos generales'!B11:C11="(Campo desplegable)","Indicar en la hoja de 'Datos generales'",'Datos generales'!B11:C11) -> Indicar en la hoja de 'Datos generales'
A6: =IF(Equipamiento!B18="Campo rellenable de descripción del equipo","Campo automático",Equipamiento!B18) -> Campo automático
A7: DATOS DE LA UTILIZACIÓN | B7: Información para el cálculo del coste
A8: Tipo de equipamiento | B8: (Campo desplegable)
A9: Indique si el equipo está amortizado | B9: (Campo desplegable)
A10: Periodo de amortización | B10: =IF(B8="(Campo desplegable)","Campo automático",VLOOKUP(B8,Referencias!A32:B33,2,FALSE)) -> Campo automático
A11: Tiempos de uso del equipo 9 | B11: Tiempo de utilización anual del equipo en horas | D11: 1
B12: Tiempo utilizado durante una UMC en hora/s y fracción | D12: 0
A13: UTILIZACIÓN DEL EQUIPO 9
A14: Energía | B14: Indique si la energía es: -Medida con un contador y valorada con las tarifas del contrato de suministro vigente -Estimada mediante facturas | D14: (Campo desplegable) | F14: ELEGIBLE EUROPEOS | G14: NO ELEGIBLE EUROPEOS | H14: MARGINAL | I14: AMORTIZACIÓN
B15: Coste de energía por UMC - IMPORTE SIN IVA (€) | D15: 0 | F15: =IF($D14="Medida con un contador","X","") | G15: =IF($D14="Estimada mediante facturas","X","") | H15: X
A16: Fungibles/Fluidos | B16: Incluir los costes - IMPORTE SIN IVA (€): Contables, número de fungibles o grupos de fungibles por coste unidad/grupo según facturas/mercado | D16: 0 | F16: X | H16: X
B17: Breve descripción de fungibles/fluidos utilizados ->
B18: Incluir los costes - IMPORTE SIN IVA (€): No contables (continuos), medida de consumo por coste UMC según facturas/mercado | D18: 0 | F18: X | H18: X
B19: Breve descripción de fungibles/fluidos utilizados ->
B20: Incluir los costes - IMPORTE SIN IVA (€): No contables (continuos), estimación de consumo por coste UMC según factura o precio de mercado | D20: 0 | G20: X | H20: X
B21: Breve descripción de fungibles/fluidos utilizados ->
A22: Amortización (si la antigüedad es inferior al periodo de amortización) | B22: Fecha de adquisición | D22: dd/mm/aaaa
B23: Valor de adquisición - IMPORTE SIN IVA (€) | D23: 0
B24: Subvención de la UE - IMPORTE SIN IVA (€) | D24: 0
B25: COSTES DE AMORTIZACIÓN ELEGIBLES PARA PROYECTOS DEL PROGRAMA MARCO POR UMC - IMPORTE SIN IVA (€) | D25: =IF(OR(B9="SÍ",B9="(Campo desplegable)"),0,((D23-D24)/B10)*(D12/D11)) -> 0 | F25: X | I25: X
B26: DIFERENCIA entre el coste de la amortización contable CSIC, C = (V/A)x t/T, donde V es el precio TOTAL de adquisición y A el periodo de amortización CSIC (véase tabla "Periodos amortización CSIC"), con el valor consignado en la casilla del coste elegible (el valor podría resultar negativo, como una corrección a la amortización acelerada que impone H2020). - IMPORTE SIN IVA (€) | D26: =IF(OR(B9="SÍ",B9="(Campo desplegable)"),0,((D23/B10)*(D12/D11))-D25) -> 0 | G26: X | I26: X
A27: COSTE TOTAL (UMC) UTILIZACIÓN DEL EQUIPO 9 | B27: → | D27: =SUM(D15,D16,D18,D20,D25,D26) -> 0 | F27: =SUMIF(F15:F26,"X",$D$15:$D$26) -> 0 | G27: =SUMIF(G15:G26,"X",$D$15:$D$26) -> 0 | H27: =SUMIF(H15:H26,"X",$D$15:$D$26) -> 0 | I27: =SUMIF(I15:I26,"X",$D$15:$D$26) -> 0
A29: MANTENIMIENTO EQUIPO 9
A30: Mantenimiento del equipo 9 (incluyendo calibraciones preprogramadas) | B30: Coste anual de reparación y mantenimiento (o media del coste de los últimos cinco años) - IMPORTE SIN IVA (€) | D30: 0
A31: COSTE TOTAL (UMC) MANTENIMIENTO EQUIPO 9 IMPORTE SIN IVA (€) | B31: → | D31: =(D30*D12/D11) -> 0 | G31: X
F32: =SUMIF(F30:F31,"X",$D$30:$D$31) -> 0 | G32: =SUMIF(G30:G31,"X",$D$30:$D$31) -> 0 | H32: =SUMIF(H30:H31,"X",$D$30:$D$31) -> 0 | I32: =SUMIF(I30:I31,"X",$D$30:$D$31) -> 0
A33: ARRANQUE/ENFRIAMIENTO EQUIPO 9
A34: Energía | B34: Energía por arranque/enfriamiento - IMPORTE SIN IVA (€) | D34: 0 | G34: X | H34: X
A35: Fungibles/Fluidos | B35: Fungibles/Fluidos por arranque/enfriamiento - IMPORTE SIN IVA (€) | D35: 0 | G35: X | H35: X
B36: Breve descripción de fungibles/fluidos utilizados ->
A37: Amortización | B37: Rellenar en caso de equipamiento en periodo de amortización
B38: Nº medio de UMC por arranque/enfriamiento | D38: 1
B39: Tiempo de arranque/enfriamiento en hora/s y fracción | D39: 0
B40: COSTES DE AMORTIZACIÓN NO ELEGIBLES PARA PROYECTOS DEL PROGRAMA MARCO - IMPORTE SIN IVA (€) | D40: =IF(OR(B9="SÍ",B9="(Campo desplegable)"),0,(D23/B10)*(D39/D11)) -> 0
B41: Amortización asociada al tiempo de arranque/enfriamiento por UMC - IMPORTE SIN IVA (€) | D41: =D40/D38 -> 0 | G41: X | I41: X
A42: COSTE TOTAL (UMC) ARRANQUE/ENFRIAMIENTO EQUIPO 9 IMPORTE SIN IVA (€) | B42: → | D42: =SUM(D34,D35,D41) -> 0 | F42: =SUMIF(F34:F41,"X",$D$34:$D$41) -> 0 | G42: =SUMIF(G34:G41,"X",$D$34:$D$41) -> 0 | H42: =SUMIF(H34:H41,"X",$D$34:$D$41) -> 0 | I42: =SUMIF(I34:I41,"X",$D$34:$D$41) -> 0
A44: CALIBRACIÓN INTERMEDIA DEL EQUIPO 9
A45: Energía | B45: Energía por calibración - IMPORTE SIN IVA (€) | D45: 0 | G45: X | H45: X
A46: Fungibles/Fluidos | B46: Fungibles/Fluidos por calibración - IMPORTE SIN IVA (€) | D46: 0 | G46: X | H46: X
B47: Breve descripción de fungibles/fluidos utilizados ->
A48: Amortización | B48: Rellenar en caso de equipamiento en periodo de amortización
B49: Nº medio de UMC por calibración | D49: 1
B50: Tiempo de la calibración en hora/s y fracción | D50: 0
B51: COSTES DE AMORTIZACIÓN NO ELEGIBLES PARA PROYECTOS DEL PROGRAMA MARCO - IMPORTE SIN IVA (€) | D51: =IF(OR(B9="SÍ",B9="(Campo desplegable)"),0,(D23/B10)*(D50/D11)) -> 0
B52: Amortización de la calibración por UMC - IMPORTE SIN IVA (€) | D52: =D51/D49 -> 0 | G52: X | I52: X
A53: COSTE TOTAL (UMC) CALIBRACIÓN INTERMEDIA DEL EQUIPO 9 (durante el transcurso de un grupo de prestaciones) IMPORTE SIN IVA (€) | B53: → | D53: =SUM(D45,D46,D52) -> 0 | F53: =SUMIF(F45:F52,"X",$D$45:$D$52) -> 0 | G53: =SUMIF(G45:G52,"X",$D$45:$D$52) -> 0 | H53: =SUMIF(H45:H52,"X",$D$45:$D$52) -> 0 | I53: =SUMIF(I45:I52,"X",$D$45:$D$52) -> 0
B55: COSTE TOTAL (UMC) EQUIPO 9 | D55: TOTAL IMPORTE SIN IVA (€) | F55: TOTAL ELEGIBLE EUROPEOS (€) | G55: TOTAL NO ELEGIBLE EUROPEOS (€) | H55: TOTAL MARGINAL (€) | I55: TOTAL AMORTIZACIÓN (€)
A56: VOLVER A EQUIPAMIENTO | B56: Suma del coste total del equipo 9 implicado en el desarrollo por UMC | D56: =SUM(D27,D31,D42,D53) -> 0 | F56: =SUMIF(F15:F52,"X",$D$15:$D$52) -> 0 | G56: =SUMIF(G15:G52,"X",$D$15:$D$52) -> 0 | H56: =SUMIF(H15:H52,"X",$D$15:$D$52) -> 0 | I56: =SUMIF(I15:I52,"X",$D$15:$D$52) -> 0

Sheet Equipo 10
A2: EQUIPO 10 (por UMC)
A4: UMC (€) | B4: =IF('Datos generales'!B11:C11="(Campo desplegable)","Indicar en la hoja de 'Datos generales'",'Datos generales'!B11:C11) -> Indicar en la hoja de 'Datos generales'
A6: =IF(Equipamiento!B19="Campo rellenable de descripción del equipo","Campo automático",Equipamiento!B19) -> Campo automático
A7: DATOS DE LA UTILIZACIÓN | B7: Información para el cálculo del coste
A8: Tipo de equipamiento | B8: (Campo desplegable)
A9: Indique si el equipo está amortizado | B9: (Campo desplegable)
A10: Periodo de amortización | B10: =IF(B8="(Campo desplegable)","Campo automático",VLOOKUP(B8,Referencias!A32:B33,2,FALSE)) -> Campo automático
A11: Tiempos de uso del equipo 10 | B11: Tiempo de utilización anual del equipo en horas | D11: 1
B12: Tiempo utilizado durante una UMC en hora/s y fracción | D12: 0
A13: UTILIZACIÓN DEL EQUIPO 10
A14: Energía | B14: Indique si la energía es: -Medida con un contador y valorada con las tarifas del contrato de suministro vigente -Estimada mediante facturas | D14: (Campo desplegable) | F14: ELEGIBLE EUROPEOS | G14: NO ELEGIBLE EUROPEOS | H14: MARGINAL | I14: AMORTIZACIÓN
B15: Coste de energía por UMC - IMPORTE SIN IVA (€) | D15: 0 | F15: =IF($D14="Medida con un contador","X","") | G15: =IF($D14="Estimada mediante facturas","X","") | H15: X
A16: Fungibles/Fluidos | B16: Incluir los costes - IMPORTE SIN IVA (€): Contables, número de fungibles o grupos de fungibles por coste unidad/grupo según facturas/mercado | D16: 0 | F16: X | H16: X
B17: Breve descripción de fungibles/fluidos utilizados ->
B18: Incluir los costes - IMPORTE SIN IVA (€): No contables (continuos), medida de consumo por coste UMC según facturas/mercado | D18: 0 | F18: X | H18: X
B19: Breve descripción de fungibles/fluidos utilizados ->
B20: Incluir los costes - IMPORTE SIN IVA (€): No contables (continuos), estimación de consumo por coste UMC según factura o precio de mercado | D20: 0 | G20: X | H20: X
B21: Breve descripción de fungibles/fluidos utilizados ->
A22: Amortización (si la antigüedad es inferior al periodo de amortización) | B22: Fecha de adquisición | D22: dd/mm/aaaa
B23: Valor de adquisición - IMPORTE SIN IVA (€) | D23: 0
B24: Subvención de la UE - IMPORTE SIN IVA (€) | D24: 0
B25: COSTES DE AMORTIZACIÓN ELEGIBLES PARA PROYECTOS DEL PROGRAMA MARCO POR UMC - IMPORTE SIN IVA (€) | D25: =IF(OR(B9="SÍ",B9="(Campo desplegable)"),0,((D23-D24)/B10)*(D12/D11)) -> 0 | F25: X | I25: X
B26: DIFERENCIA entre el coste de la amortización contable CSIC, C = (V/A)x t/T, donde V es el precio TOTAL de adquisición y A el periodo de amortización CSIC (véase tabla "Periodos amortización CSIC"), con el valor consignado en la casilla del coste elegible (el valor podría resultar negativo, como una corrección a la amortización acelerada que impone H2020). - IMPORTE SIN IVA (€) | D26: =IF(OR(B9="SÍ",B9="(Campo desplegable)"),0,((D23/B10)*(D12/D11))-D25) -> 0 | G26: X | I26: X
A27: COSTE TOTAL (UMC) UTILIZACIÓN DEL EQUIPO 10 | B27: → | D27: =SUM(D15,D16,D18,D20,D25,D26) -> 0 | F27: =SUMIF(F15:F26,"X",$D$15:$D$26) -> 0 | G27: =SUMIF(G15:G26,"X",$D$15:$D$26) -> 0 | H27: =SUMIF(H15:H26,"X",$D$15:$D$26) -> 0 | I27: =SUMIF(I15:I26,"X",$D$15:$D$26) -> 0
A29: MANTENIMIENTO EQUIPO 10
A30: Mantenimiento del equipo 10 (incluyendo calibraciones preprogramadas) | B30: Coste anual de reparación y mantenimiento (o media del coste de los últimos cinco años) - IMPORTE SIN IVA (€) | D30: 0
A31: COSTE TOTAL (UMC) MANTENIMIENTO EQUIPO 10 IMPORTE SIN IVA (€) | B31: → | D31: =(D30*D12/D11) -> 0 | G31: X
F32: =SUMIF(F30:F31,"X",$D$30:$D$31) -> 0 | G32: =SUMIF(G30:G31,"X",$D$30:$D$31) -> 0 | H32: =SUMIF(H30:H31,"X",$D$30:$D$31) -> 0 | I32: =SUMIF(I30:I31,"X",$D$30:$D$31) -> 0
A33: ARRANQUE/ENFRIAMIENTO EQUIPO 10
A34: Energía | B34: Energía por arranque/enfriamiento - IMPORTE SIN IVA (€) | D34: 0 | G34: X | H34: X
A35: Fungibles/Fluidos | B35: Fungibles/Fluidos por arranque/enfriamiento - IMPORTE SIN IVA (€) | D35: 0 | G35: X | H35: X
B36: Breve descripción de fungibles/fluidos utilizados ->
A37: Amortización | B37: Rellenar en caso de equipamiento en periodo de amortización
B38: Nº medio de UMC por arranque/enfriamiento | D38: 1
B39: Tiempo de arranque/enfriamiento en hora/s y fracción | D39: 0
B40: COSTES DE AMORTIZACIÓN NO ELEGIBLES PARA PROYECTOS DEL PROGRAMA MARCO - IMPORTE SIN IVA (€) | D40: =IF(OR(B9="SÍ",B9="(Campo desplegable)"),0,(D23/B10)*(D39/D11)) -> 0
B41: Amortización asociada al tiempo de arranque/enfriamiento por UMC - IMPORTE SIN IVA (€) | D41: =D40/D38 -> 0 | G41: X | I41: X
A42: COSTE TOTAL (UMC) ARRANQUE/ENFRIAMIENTO EQUIPO 10 IMPORTE SIN IVA (€) | B42: → | D42: =SUM(D34,D35,D41) -> 0 | F42: =SUMIF(F34:F41,"X",$D$34:$D$41) -> 0 | G42: =SUMIF(G34:G41,"X",$D$34:$D$41) -> 0 | H42: =SUMIF(H34:H41,"X",$D$34:$D$41) -> 0 | I42: =SUMIF(I34:I41,"X",$D$34:$D$41) -> 0
A44: CALIBRACIÓN INTERMEDIA DEL EQUIPO 10
A45: Energía | B45: Energía por calibración - IMPORTE SIN IVA (€) | D45: 0 | G45: X | H45: X
A46: Fungibles/Fluidos | B46: Fungibles/Fluidos por calibración - IMPORTE SIN IVA (€) | D46: 0 | G46: X | H46: X
B47: Breve descripción de fungibles/fluidos utilizados ->
A48: Amortización | B48: Rellenar en caso de equipamiento en periodo de amortización
B49: Nº medio de UMC por calibración | D49: 1
B50: Tiempo de la calibración en hora/s y fracción | D50: 0
B51: COSTES DE AMORTIZACIÓN NO ELEGIBLES PARA PROYECTOS DEL PROGRAMA MARCO - IMPORTE SIN IVA (€) | D51: =IF(OR(B9="SÍ",B9="(Campo desplegable)"),0,(D23/B10)*(D50/D11)) -> 0
B52: Amortización de la calibración por UMC - IMPORTE SIN IVA (€) | D52: =D51/D49 -> 0 | G52: X | I52: X
A53: COSTE TOTAL (UMC) CALIBRACIÓN INTERMEDIA DEL EQUIPO 10 (durante el transcurso de un grupo de prestaciones) IMPORTE SIN IVA (€) | B53: → | D53: =SUM(D45,D46,D52) -> 0 | F53: =SUMIF(F45:F52,"X",$D$45:$D$52) -> 0 | G53: =SUMIF(G45:G52,"X",$D$45:$D$52) -> 0 | H53: =SUMIF(H45:H52,"X",$D$45:$D$52) -> 0 | I53: =SUMIF(I45:I52,"X",$D$45:$D$52) -> 0
B55: COSTE TOTAL (UMC) EQUIPO 10 | D55: TOTAL IMPORTE SIN IVA (€) | F55: TOTAL ELEGIBLE EUROPEOS (€) | G55: TOTAL NO ELEGIBLE EUROPEOS (€) | H55: TOTAL MARGINAL (€) | I55: TOTAL AMORTIZACIÓN (€)
A56: VOLVER A EQUIPAMIENTO | B56: Suma del coste total del equipo 10 implicado en el desarrollo por UMC | D56: =SUM(D27,D31,D42,D53) -> 0 | F56: =SUMIF(F15:F52,"X",$D$15:$D$52) -> 0 | G56: =SUMIF(G15:G52,"X",$D$15:$D$52) -> 0 | H56: =SUMIF(H15:H52,"X",$D$15:$D$52) -> 0 | I56: =SUMIF(I15:I52,"X",$D$15:$D$52) -> 0

Sheet Referencias
A1: PERSONAL CSIC DE PLANTILLA (COSTES/HORA) | C1: PERSONAL CSIC CONTRATADO (COSTES/HORA) | E1: PERSONAL CSIC ASOCIADO A CONCEPTOS NO ELEGIBLES (COSTES/HORA) | G1: UNIDADES DE MEDIDA | H1: LISTA DE CENTROS/INSTITUTOS
A2: (Campo desplegable) | B2: 0 | C2: (Campo desplegable) | D2: 0 | E2: (Campo desplegable) | F2: 0 | G2: (Campo desplegable) | H2: (Campo desplegable)
A3: Profesor de investigación | B3: 64.7 | C3: G1 / 1G / M3 | D3: 34.1 | E3: Profesor de investigación | F3: 64.7 | G3: área | H3: CENTRO ANDALUZ DE BIOLOGIA DEL DESARROLLO (CABD-050167)
A4: Investigador científico | B4: 57.86 | C4: G2 / 2G / M2 | D4: 29.51 | E4: Investigador científico | F4: 57.86 | G4: área/ unidad de tiempo | H4: CENTRO ANDALUZ DE BIOLOGIA MOLECULAR Y MEDICINA REGENERATIVA (CABIMER-050564)
A5: Científico titular | B5: 48.43 | C5: G3 / 3G / M1 | D5: 24.8 | E5: Científico titular | F5: 48.43 | G5: ensayo o proceso | H5: CENTRO DE ASTROBIOLOGIA (CAB-010664)
A6: Tecnólogos de OPI | B6: 41.45 | C6: G4 / 4G / E2 | D6: 22.23 | E6: Tecnólogos de OPI | F6: 41.45 | G6: ensayo o proceso/ unidad de tiempo | H6: CENTRO DE AUTOMATICA Y ROBOTICA (CAR-010564)
A7: Técnico Superior Especializado OPI | B7: 41.11 | C7: G5 / E1 | D7: 21.87 | E7: Técnico Superior Especializado OPI | F7: 41.11 | G7: hora o fracción | H7: CENTRO DE BIOLOGIA MOLECULAR SEVERO OCHOA (CBM-050105)
A8: Técnico Especializado OPI | B8: 35.22 | C8: E0 | D8: 14.7 | E8: Técnico Especializado OPI | F8: 35.22 | G8: informe | H8: CENTRO DE BIOTECNOLOGIA Y GENOMICA DE PLANTAS (CBGP-060161)
A9: Ayudante de investigación | B9: 25.89 | C9: Doctor FC1 | D9: 46.86 | E9: Ayudante de investigación | F9: 25.89 | G9: muestra o grupo de muestras | H9: CENTRO DE CIENCIA Y TECNOLOGIAS CUANTICAS (QUARC-220101)
A10: Auxiliar de investigación | B10: 23.18 | C10: Doctor FC2 | D10: 41.62 | E10: Auxiliar de investigación | F10: 23.18 | G10: muestra o grupo de muestras/ unidad de tiempo | H10: CENTRO DE CIENCIAS HUMANAS Y SOCIALES (CCHS-120307)
A11: Investigador Distinguido | B11: 37.67 | C11: Doctor FC3 | D11: 37.17 | E11: Investigador Distinguido | F11: 37.67 | H11: CENTRO DE EDAFOLOGIA Y BIOLOGIA APLICADA DEL SEGURA (CEBAS-090202)
A12: G1 / 1G / M3 | B12: 34.1 | C12: Doctor FC4 | D12: 34.14 | E12: G1 / 1G / M3 | F12: 34.1 | H12: CENTRO DE ESTUDIOS AVANZADOS DE BLANES (CEAB-000107)
A13: G2 / 2G / M2 | B13: 29.51 | C13: Titulado Superior FC1 | D13: 37.17 | E13: G2 / 2G / M2 | F13: 29.51 | H13: CENTRO DE FISICA DE MATERIALES (CFM-010162)
A14: G3 / 3G / M1 | B14: 24.8 | C14: Titulado Superior FC 2 | D14: 34.14 | E14: G3 / 3G / M1 | F14: 24.8 | H14: CENTRO DE FISICA MIGUEL A. CATALAN (CFMAC-010105)
A15: G4 / 4G / E2 | B15: 22.23 | E15: G4 / 4G / E2 | F15: 22.23 | H15: CENTRO DE FISICA TEORICA Y MATEMATICAS (CFTMAT-000260)
A16: G5 / E1 | B16: 21.87 | E16: G5 / E1 | F16: 21.87 | H16: CENTRO DE INVESTIGACION AGRIGENOMICA (CRAG-750102)
A17: E0 | B17: 14.7 | E17: E0 | F17: 14.7 | H17: CENTRO DE INVESTIGACION DEL CANCER (CIC-050108)
A18: Doctor FC1 | B18: 46.86 | E18: Doctor FC1 | F18: 46.86 | H18: CENTRO DE INVESTIGACION ECOLOGICA Y APLICACIONES FORESTALES (CREAF-060461)
A19: Doctor FC2 | B19: 41.62 | E19: Doctor FC2 | F19: 41.62 | H19: CENTRO DE INVESTIGACION EN NANOCIENCIA Y NANOTECNOLOGIA (CIN2-010268)
A20: Doctor FC3 | B20: 37.17 | E20: Doctor FC3 | F20: 37.17 | H20: CENTRO DE INVESTIGACION EN NANOMATERIALES Y NANOTECNOLOGIA (CINN-010269)
A21: Doctor FC4 | B21: 34.14 | E21: Doctor FC4 | F21: 34.14 | H21: CENTRO DE INVESTIGACION EN SANIDAD ANIMAL (CISA-100103)
A22: Titulado Superior FC1 | B22: 37.17 | E22: Titulado Superior FC1 | F22: 37.17 | H22: CENTRO DE INVESTIGACION Y DESARROLLO PASCUAL VILA (CID-040105)
A23: Titulado Superior FC 2 | B23: 34.14 | E23: Titulado Superior FC 2 | F23: 34.14 | H23: CENTRO DE INVESTIGACIONES BIOLOGICAS MARGARITA SALAS (CIB-050204)
H24: CENTRO DE INVESTIGACIONES CIENTIFICAS ISLA DE LA CARTUJA (CICCARTUJA-020103)
A25: Campaña 2025: Tabla IVA | H25: CENTRO DE INVESTIGACIONES INTERDISCIPLINARES DE ALCALA (CI2A-050602)
A26: IVA | B26: 0.21 | H26: CENTRO DE INVESTIGACIONES SOBRE DESERTIFICACION (CIDE-080164)
A27: IVA no Deducible | B27: 0.29 | H27: CENTRO DE NEUROCIENCIAS CAJAL (CNC-050605)
A28: % Marginal | B28: 0.173 | H28: CENTRO DE QUIMICA ORGANICA LORA TAMAYO (CENQUIOR-020306)
H29: CENTRO DE QUIMICA Y MATERIALES DE ARAGON (CEQMA-020160)
A30: CSIC BIENES ADQUIRIDOS | B30: PERIODO AMORTIZACIÓN (años)* | H30: CENTRO DE RECURSOS FITOGENETICOS Y AGRICULTURA SOSTENIBLE (CRF-600001)
A31: (Campo desplegable) | B31: 0 | H31: CENTRO MEDITERRANEO DE INVESTIGACIONES MARINAS Y AMBIENTALES (CMIMA-070105)
A32: Equipos e Instrumental Científico | B32: 5 | H32: CENTRO NACIONAL DE ACELERADORES (CNA-010169)
A33: Equipos para Proceso de Información | B33: 3 | H33: CENTRO NACIONAL DE BIOTECNOLOGIA (CNB-050402)
A34: * Los bienes adquiridos con anterioridad a 2021 se consideran amortizados | H34: CENTRO NACIONAL DE INVESTIGACIONES METALURGICAS (CENIM-040201)
H35: CENTRO NACIONAL DE MICROELECTRONICA (CNM-010207)
H36: CENTRO OCEANOGRAFICO DE A CORUÑA (COAC-070501)
H37: CENTRO OCEANOGRAFICO DE CADIZ (COCAD-070509)
H38: CENTRO OCEANOGRAFICO DE CANARIAS (COC-070507)
H39: CENTRO OCEANOGRAFICO DE GIJON (COG-070508)
H40: CENTRO OCEANOGRAFICO DE ILLES BALEARS (COB-070506)
H41: CENTRO OCEANOGRAFICO DE MALAGA (COMA-070503)
H42: CENTRO OCEANOGRAFICO DE MURCIA (COMU-070505)
H43: CENTRO OCEANOGRAFICO DE SANTANDER (COST-070502)
H44: CENTRO OCEANOGRAFICO DE VIGO (COV-070504)
H45: ESCUELA DE ESTUDIOS ARABES (EEA-130402)
H46: ESCUELA ESPANOLA DE HISTORIA Y ARQUEOLOGIA (EEHAR-120202)
... H150: CSIC - ORGANIZACION CENTRAL (CSIC ORGC-902001)
